Workbook

Sheet Cover
B2: HOSPITAL 360
B3: Strategic Healthcare Management & Analytics Model
B4: Complete 12-Step Practical Project — Master Model Workbook
B6: Locked project assumptions:
B7: Location | C7: Kangra–Palampur corridor, Himachal Pradesh
B8: Model type | C8: 100-bed regional multispecialty hospital
B9: Launch scale | C9: 75–80 operational beds at Year 1, scaling to 100 beds
B10: Base Case CAPEX | C10: ₹50 crore (Lean ₹40 crore / Upper ₹60 crore)
B11: Nature of model | C11: Hypothetical academic strategic model — not an existing hospital
B12: Prepared for | C12: MBA Pharma & Healthcare Management capstone — Dev, Shoolini Business School
B13: Decision framework | C13: CONDITIONAL GO pending site, demand, regulatory & financial due diligence
B15: Data labelling convention used throughout this workbook:
B16: Actual Public Data | C16: Verifiable published figures (Census, Govt/HP Health Dept, hospital public disclosures) — cited in Source Register.
B17: Benchmark | C17: Industry / peer-hospital norms used for planning where no local figure exists.
B18: Assumption | C18: Project-team judgement calls, explicitly flagged, used where data is unavailable.
B19: Calculated Value | C19: Derived by formula from the above three categories.
B21: Synthetic data used in the Analytics sheets (21–29) is explicitly labelled SYNTHETIC and must never be presented as real patient or hospital data.
B23: Workbook map:
C24: • 02_Assumptions, 03_Himachal_Market_Data, Source_Register
C25: • 04_Location_Analysis
C26: • 05_Hospital_Profile, 06_Hospital_Design, 07_Bed_Mix, 08_Department_Planning
C27: • 09_Manpower
C28: • 10_CAPEX, 11_OPEX, 12_Revenue, 13_P&L, 14_Cash_Flow, 15_Break_Even, 16_Sensitivity
C29: • 17_Operations_KPIs, 18_Patient_Flow
C30: • 19_NABH_Readiness
C31: • 20_Competitor_Benchmark
C32: • 21–29_Analytics (synthetic data + star-schema dashboards)

Sheet 01_Project_Charter
A1: PROJECT CHARTER — HOSPITAL 360
A2: One-page charter summary (full narrative in Hospital_360_Project_Charter.docx)
A3: Project Title | B3: Hospital 360 — Strategic Healthcare Management & Analytics Model for a 100-Bed Regional Multispecialty Hospital in the Kangra–Palampur Corridor, Himachal Pradesh
A4: Problem Statement | B4: Residents of the Kangra–Palampur corridor currently rely on an overstretched public tertiary hospital (RPGMC Tanda) or must travel to Chandigarh/Delhi for many tertiary-care needs, while the private sector in-corridor remains limited largely to one established player. There is a case to test whether a well-positioned, NABH-oriented 100-bed private multispecialty hospital can profitably close part of this access gap.
A5: Objectives | B5: 1) Quantify the market opportunity for a 100-bed hospital in the corridor. 2) Test location feasibility against transparent weighted criteria. 3) Design the service/business model, capacity plan and manpower structure. 4) Build an integrated financial model (Base/Lean/Upper cases) to test viability. 5) Define an operations and NABH-oriented quality blueprint. 6) Benchmark competitors. 7) Build an analytics/Power-BI-ready reporting layer. 8) Arrive at a final, evidence-based Go/No-Go strategic recommendation.
A6: Scope | B6: A hypothetical, academic strategic and financial model — not an existing hospital and not a live investment proposal. Covers market analysis, location feasibility, service design, capacity & manpower planning, a 10-year financial model, operations & quality frameworks, competitor benchmarking, and a synthetic-data analytics layer.
A7: Key Assumptions | B7: 100 licensed beds, launched at 75–80 beds; ₹50 Cr Base Case CAPEX (Lean ₹40 Cr / Upper ₹60 Cr); Kangra–Palampur corridor location locked per brief; all financial/operational figures explicitly tagged Actual Public Data, Benchmark, Assumption or Calculated Value; analytics-layer data is synthetic and explicitly labelled as such.
A8: Stakeholders | B8: Academic evaluators (MBA Pharma & Healthcare Management programme); hypothetical promoter/investor group; hypothetical hospital management team; hypothetical regulatory bodies (State Health Department, NABH, NABL); hypothetical local community & referral network.
A9: Research Questions | B9: Is there a quantifiable, evidence-based demand gap for tertiary multispecialty care in the Kangra–Palampur corridor? Is the Kangra–Palampur location feasible on transparent weighted criteria? Does a ₹50 Cr Base Case 100-bed model achieve break-even and acceptable debt-service coverage within a reasonable horizon? What quality, operations and analytics systems are needed to make the hospital NABH-ready and management-controllable?
A10: Methodology | B10: Desk research on publicly available demographic and healthcare-infrastructure data (Census 2011, known regional facilities); benchmark-driven financial and operational modelling using standard Indian private-hospital planning norms where local data is unavailable; weighted-criteria scoring for location feasibility; synthetic data generation to demonstrate an analytics/Power BI reporting layer; structured strategic synthesis into a final Go/No-Go recommendation.
A11: Deliverables | B11: Hospital_360_HP_Master_Model.xlsx (this workbook); Hospital_360_Source_Register.xlsx; Hospital_360_Synthetic_Data.xlsx; supporting Word documents (Project Charter, Market Analysis, Location Feasibility Notes, Service Model, Manpower Assumptions, Operations SOP, Quality Framework, Final Report, Final Strategy); Hospital_360_Final_Presentation.pptx; an interactive HTML analytics dashboard in place of a native Power BI .pbix file.
A12: Decision Framework | B12: CONDITIONAL GO is the default decision status throughout this project until site-specific, demand-specific, regulatory and financial due diligence are independently completed — this model supports, but does not replace, that due diligence.

Sheet Source_Register
A1: SOURCE REGISTER
A2: Every externally-sourced figure used across this workbook, with citation
A3: # | B3: Data Point | C3: Value Used In Model | D3: Category | E3: Source | F3: Year
A4: 1 | B4: Kangra district population (2011 Census) | C4: 1,510,075 (density 263/km²) | D4: Actual Public Data | E4: Census of India 2011 / Registrar General & Census Commissioner | F4: 2011
A5: 2 | B5: Himachal Pradesh state population (2011 Census) | C5: 6,864,602 | D5: Actual Public Data | E5: Census of India 2011 | F5: 2011
A6: 3 | B6: Kangra district decadal growth rate | C6: 12.77% (2001–2011) | D6: Actual Public Data | E6: Census of India 2011 | F6: 2011
A7: 4 | B7: Kangra tehsils in the corridor catchment (Kangra, Palampur, Dharamshala, Baijnath, Nagrota Bagwan tehsils) | C7: ~590,000 combined tehsil population | D7: Calculated Value | E7: Sum of Census 2011 tehsil-level population (see 03_Himachal_Market_Data) | F7: 2011
A8: 5 | B8: Projected 2026 district population | C8: Grown from 2011 base at ~1.3%/yr compounded | D8: Assumption | E8: Project team — extrapolation of 2001–2011 CAGR; no 2021 Census was conducted | F8: 2026
A9: 6 | B9: HP doctor–population ratio / rural health infra gaps | C9: Directional benchmark only | D9: Benchmark | E9: National Health Profile / HP Economic Survey (general public-domain reporting on HP healthcare infrastructure) | F9: Various
A10: 7 | B10: India private tertiary hospital CAPEX per bed (Tier-2/3 city) | C10: ₹45–65 lakh per bed | D10: Benchmark | E10: Industry norm used in Indian hospital feasibility studies (project-team compiled benchmark range) | F10: Recent
A11: 8 | B11: India private hospital OPEX staff cost as % of revenue | C11: 38–45% of revenue | D11: Benchmark | E11: Industry norm for 100–150 bed private multispecialty hospitals | F11: Recent
A12: 9 | B12: Mature-hospital occupancy for break-even in Tier-2/3 India | C12: 55–65% | D12: Benchmark | E12: Industry norm for regional multispecialty hospitals | F12: Recent
A13: 10 | B13: NABH standard structure (AAC, COP, MOM, PRE, HIC, PSQ, ROM, FMS, HRM, IMS) | C13: 10 chapters used as-is | D13: Actual Public Data | E13: National Accreditation Board for Hospitals & Healthcare Providers (NABH) — public standards framework naming convention | F13: Current
A14: 11 | B14: Fortis Hospital Kangra, RPGMC Tanda, Zonal Hospital Dharamshala, Civil Hospital Palampur — presence & broad positioning | C14: Named as competitor set | D14: Actual Public Data | E14: Publicly known regional healthcare providers in the Kangra–Palampur corridor | F14: Current
A15: 12 | B15: All bed-mix, department, manpower, financial and analytics figures not listed above | C15: See respective sheets | D15: Assumption / Calculated Value | E15: Project team — built for this hypothetical academic model; not sourced from any real hospital's financials | F15: 2026
A17: This register exists so every number elsewhere in the workbook can be traced back to Actual Public Data, a named Benchmark, an explicit Assumption, or a Calculated Value. Update this sheet whenever a new external figure is introduced anywhere in the model.

Sheet 02_Assumptions
A1: PROJECT ASSUMPTION REGISTER
A2: Master list of every planning assumption feeding the model — change here, not in downstream sheets
A3: # | B3: Assumption | C3: Value | D3: Unit | E3: Category | F3: Rationale / Note
A4: 1 | B4: Hospital licensed bed capacity | C4: 100 | D4: beds | E4: Assumption | F4: Locked project scope per brief
A5: 2 | B5: Beds operational at launch (Year 1) | C5: 78 | D5: beds | E5: Assumption | F5: Phased launch at 75–80 beds as instructed
A6: 3 | B6: Beds operational at maturity (Year 5) | C6: 100 | D6: beds | E6: Assumption | F6: Full licensed capacity reached by Year 5
A7: 4 | B7: Base Case project CAPEX | C7: 50 | D7: ₹ Cr | E7: Assumption | F7: Locked Base Case per brief
A8: 5 | B8: Lean Case project CAPEX | C8: 40 | D8: ₹ Cr | E8: Assumption | F8: Locked Lean scenario per brief
A9: 6 | B9: Upper Case project CAPEX | C9: 60 | D9: ₹ Cr | E9: Assumption | F9: Locked Upper scenario per brief
A10: 7 | B10: Land requirement | C10: 4 | D10: acres | E10: Benchmark | F10: Typical land norm for a 100-bed multispecialty facility with future expansion
A11: 8 | B11: Built-up area | C11: 150000 | D11: sq ft | E11: Benchmark | F11: ~1,500 sq ft per licensed bed — standard Indian tertiary-care planning norm
A12: 9 | B12: Construction & fit-out period | C12: 24 | D12: months | E12: Benchmark | F12: Typical for a greenfield 100-bed hospital in a hill-state Tier-3 location
A13: 10 | B13: Debt : Equity ratio for CAPEX funding | C13: 0.65 | D13: ratio (D) | E13: Assumption | F13: 65% debt / 35% equity — typical structure for hospital project finance in India
A14: 11 | B14: Term loan interest rate | C14: 0.105 | D14: % p.a. | E14: Benchmark | F14: Indicative secured project-finance rate for healthcare infrastructure
A15: 12 | B15: Loan tenure | C15: 10 | D15: years | E15: Assumption | F15: Standard healthcare infra term loan tenure incl. moratorium
... A33: 30 | B33: Discount rate (WACC) for NPV | C33: 0.13 | D33: % p.a. | E33: Assumption | F33: Blended cost of debt (post-tax) and equity for a healthcare infra project
A35: Named cells in this sheet (yellow fill, blue font) are the single edit-point for every downstream sheet — CAPEX, OPEX, Revenue, Manpower and Analytics all reference 02_Assumptions rather than hardcoding these numbers again.

Sheet 03_Himachal_Market_Data
A1: HIMACHAL PRADESH & KANGRA–PALAMPUR MARKET DATA
A2: Every figure tagged Actual Public Data / Benchmark / Assumption / Calculated Value
A3: A. DEMOGRAPHIC BASE (CATCHMENT)
A4: Metric | B4: Value | C4: Unit | D4: Category | E4: Note / Source
A5: Himachal Pradesh — total population (2011 Census) | B5: 6864602 | C5: persons | D5: Actual Public Data | E5: Census of India 2011
A6: Kangra district — total population (2011 Census) | B6: 1510075 | C6: persons | D6: Actual Public Data | E6: Census of India 2011; most populous HP district
A7: Kangra district — population density | B7: 263 | C7: per km² | D7: Actual Public Data | E7: Census of India 2011
A8: Kangra district — decadal growth rate (2001–11) | B8: 0.1277 | C8: % | D8: Actual Public Data | E8: Census of India 2011
A9: Core catchment tehsils (Kangra, Palampur, Dharamshala, Baijnath, Nagrota Bagwan) | B9: 585508 | C9: persons | D9: Calculated Value | E9: Sum of 2011 tehsil populations: 97,568+189,276+136,536+95,229+76,899
A10: Assumed annual catchment growth (extrapolated) | B10: 0.013 | C10: % p.a. | D10: Assumption | E10: Derived from 2001–11 CAGR; no full 2021 Census available
A11: Projected 2026 core catchment population | B11: =ROUND($B$9*(1+$B$10)^15,0) -> 710681 | C11: persons | D11: Calculated Value | E11: Formula-driven from rows above
A12: Secondary/referral catchment (wider Kangra + adjoining districts) | B12: 2200000 | C12: persons | D12: Assumption | E12: Planning estimate for referral-level draw, not primary catchment
A14: B. PUBLIC HEALTHCARE INFRASTRUCTURE IN THE CORRIDOR
A15: Facility | B15: Indicative Bed Strength | C15: Type | D15: Category | E15: Note
A16: Dr. Rajendra Prasad Govt. Medical College (RPGMC), Tanda | B16: 950 | C16: Govt. tertiary teaching hospital | D16: Actual Public Data | E16: Largest public tertiary facility in the corridor — primary public competitor for complex/tertiary cases
A17: Zonal Hospital, Dharamshala | B17: 200 | C17: Govt. secondary care | D17: Benchmark | E17: District-level referral hospital; bed count is an indicative public planning figure
A18: Civil Hospital, Palampur | B18: 100 | C18: Govt. secondary care | D18: Benchmark | E18: Sub-divisional level facility
A19: Fortis Hospital, Kangra | B19: 100 | C19: Private secondary/tertiary | D19: Actual Public Data | E19: Key private-sector competitor already present in the corridor
A20: Other private nursing homes / clinics (aggregate) | B20: 150 | C20: Private — small format | D20: Assumption | E20: Aggregate planning estimate; highly fragmented small-bed private sector
A22: Total indicative public + private beds in corridor | B22: =SUM(B16:B20) -> 1500
A24: C. MARKET GAP INDICATORS
A25: Metric | B25: Value | C25: Unit | D25: Category | E25: Note
A26: Implied beds per 1,000 population (corridor, public+private) | B26: =ROUND(B22/(B9/1000),2) -> 2.56 | C26: beds/1,000 | D26: Calculated Value | E26: Corridor bed base ÷ core catchment population, per 1,000
A27: WHO-referenced planning norm (general guidance) | B27: 3 | C27: beds/1,000 | D27: Benchmark | E27: Commonly cited international planning benchmark, used only directionally for a hill-state corridor
A28: Directional inference | B28: Corridor is tertiary-capacity constrained outside RPGMC Tanda; private multispecialty options remain limited to one major player (Fortis Kangra) | C28: — | D28: Assumption | E28: Project team interpretation — not an official capacity-gap certification
A30: This sheet feeds the market-opportunity narrative in Hospital_360_HP_Market_Analysis.docx. Kangra population and growth-rate figures are Actual Public Data (Census 2011); all corridor-level bed-capacity synthesis and gap inference are Calculated/Assumption and are explicitly flagged as such — no 2021 Census exists to update the base year.

Sheet 04_Location_Analysis
A1: LOCATION FEASIBILITY SCORECARD — KANGRA–PALAMPUR CORRIDOR
A2: Weighted 1–5 scoring against locked location per project brief
A3: Criterion | B3: Weight | C3: Score (1–5) | D3: Weighted Score | E3: Rationale
A4: Catchment population & density | B4: 0.18 | C4: 4 | D4: =B4*C4 -> 0.72 | E4: Core corridor catchment ~5.9 lakh, secondary draw ~22 lakh — strong for a 100-bed facility
A5: Accessibility (road/rail/air linkage) | B5: 0.14 | C5: 4 | D5: =B5*C5 -> 0.56 | E5: NH154 corridor links Kangra–Palampur–Dharamshala; Gaggal airport ~20–30 min drive from key nodes
A6: Existing healthcare ecosystem (referral-in potential from smaller facilities) | B6: 0.14 | C6: 4 | D6: =B6*C6 -> 0.56 | E6: Civil Hospital Palampur, smaller nursing homes and PHCs create a natural referral base
A7: Competitive intensity | B7: 0.12 | C7: 3 | D7: =B7*C7 -> 0.36 | E7: RPGMC Tanda (public tertiary) and Fortis Kangra (private) already present — moderate, not saturated
A8: Land availability & cost | B8: 0.12 | C8: 3 | D8: =B8*C8 -> 0.36 | E8: Hill-state topography constrains large flat parcels; land cost lower than metro but site assembly takes time
A9: Utility & infrastructure readiness (power, water, telecom) | B9: 0.1 | C9: 4 | D9: =B9*C9 -> 0.4 | E9: Established township infrastructure across Kangra/Palampur/Dharamshala
A10: Workforce availability (clinical & nursing talent pool) | B10: 0.08 | C10: 3 | D10: =B10*C10 -> 0.24 | E10: Proximity to RPGMC Tanda medical college aids recruitment; retention in a hill town is a known challenge
A11: Tourism / floating population (medical + wellness upside) | B11: 0.06 | C11: 4 | D11: =B11*C11 -> 0.24 | E11: Dharamshala–McLeodganj tourism corridor adds a non-resident patient/wellness opportunity
A12: Expansion potential (land banking for future phases) | B12: 0.06 | C12: 3 | D12: =B12*C12 -> 0.18 | E12: Feasible but subject to site-specific due diligence
A13: TOTAL / WEIGHTED SCORE (out of 5.0) | B13: =SUM(B4:B12) -> 1 | D13: =SUM(D4:D12) -> 3.62
A15: Interpretation band: 4.0–5.0 Strong Go · 3.0–3.9 Conditional Go (site-specific diligence required) · below 3.0 Reassess. Weights and scores are Assumption-level judgement calls by the project team, not a certified site-selection audit. Do not claim site-level feasibility without formal due diligence (soil test, legal title, zoning clearance, water table study).

Sheet 05_Hospital_Profile
A1: HOSPITAL BUSINESS MODEL CANVAS
A2: Hospital 360 — 100-bed regional multispecialty concept
A3: Value Proposition | B3: Trusted, accessible, NABH-oriented multispecialty tertiary care for the Kangra–Palampur corridor — reducing the need for patients to travel to Chandigarh/Delhi for advanced treatment, while offering Dharamshala's tourism/floating population a dependable emergency and wellness option.
A4: Customer Segments | B4: Resident catchment population (~5.9 lakh core, ~22 lakh secondary); domestic & international tourists visiting Dharamshala–McLeodganj; referral patients from smaller nursing homes/PHCs; government/insurance-scheme beneficiaries (Ayushman Bharat, HP state schemes, CGHS/ECHS).
A5: Channels | B5: Direct walk-in OPD; referral network with peripheral hospitals and PHCs; empanelment with insurers/TPAs and government schemes; digital presence (website, teleconsultation, appointment app); corporate & institutional health-checkup tie-ups; hotel/tour-operator wellness tie-ups.
A6: Customer Relationships | B6: Personalised consultant-led care teams; dedicated patient-relationship desk for out-station/tourist patients; post-discharge follow-up and teleconsultation; loyalty/health-card programme for repeat local families.
A7: Revenue Streams | B7: IPD (bed charges, OT, ICU) ~62% · OPD consultations ~14% · Diagnostics (lab + imaging) ~14% · Pharmacy ~10% · Ancillary (health check packages, ambulance, wellness) — see 12_Revenue for the full build-up.
A8: Key Resources | B8: Clinical talent (consultants, nursing, allied health) · 100-bed licensed physical infrastructure · diagnostic & OT equipment · NABH-oriented quality systems · HIS/EMR & Power BI analytics layer · brand & referral relationships.
A9: Key Activities | B9: Clinical service delivery (OPD/IPD/Emergency/OT) · quality & accreditation management · manpower development · demand generation & referral management · digital health records and analytics · community health outreach.
A10: Key Partners | B10: RPGMC Tanda & academic institutions (training/referral) · insurers & TPAs · government health schemes · diagnostic/pharma equipment OEMs · ambulance & logistics partners · hospitality sector (Dharamshala tourism tie-ups).
A11: Cost Structure | B11: Manpower (largest single line, ~40% of OPEX) · consumables & pharmacy · equipment maintenance & depreciation · utilities & facility management · marketing/referral development · quality/accreditation costs — see 11_OPEX.
A13: SERVICE PORTFOLIO BY PHASE
A14: Phase | B14: Services
A15: Phase 1 (Launch, 75–80 beds) | B15: General Medicine, General Surgery, Obstetrics & Gynaecology, Paediatrics, Orthopaedics, Emergency & Trauma, ICU/HDU, Anaesthesia, Radiology (X-ray/USG/CT), Laboratory, Pharmacy, Physiotherapy.
A16: Phase 2 (Stabilisation, Year 2–3, scaling to ~90 beds) | B16: Cardiology & Cath Lab, Nephrology & Dialysis, Gastroenterology, Urology, ENT, Ophthalmology, Oncology OPD/Day-care Chemotherapy, Advanced Imaging (MRI).
A17: Phase 3 (Demand-driven, Year 4–5, 100 beds) | B17: Neurology/Neurosurgery, Cardiac Surgery (subject to demand study), Renal Transplant work-up, Advanced Oncology, Fertility/IVF, Executive Health & Wellness Centre (tourism-linked).

Sheet 06_Hospital_Design
A1: CAPACITY, BUILT-UP AREA & ZONING PLAN
A2: Conceptual planning — not an architectural drawing
A3: A. LAND & BUILT-UP AREA
A4: Parameter | B4: Value | C4: Unit | D4: Category | E4: Note
A5: Land parcel | B5: ='02_Assumptions'!$C$10 -> 4 | C5: acres | D5: Assumption | E5: Linked to 02_Assumptions
A6: Total built-up area (all floors) | B6: ='02_Assumptions'!$C$11 -> 150000 | C6: sq ft | D6: Assumption | E6: Linked to 02_Assumptions — ~1,500 sq ft/licensed bed norm
A7: Clinical / diagnostic block | B7: =B5*0.45 -> 1.8 | C7: sq ft | D7: Calculated Value | E7: 45% of built-up area — OPD, diagnostics, OT, ICU, IPD wards
A8: Support services block (CSSD, pharmacy store, kitchen, laundry, mortuary) | B8: =B5*0.15 -> 0.6 | C8: sq ft | D8: Calculated Value | E8: 15% of built-up area
A9: Administrative & academic block | B9: =B5*0.1 -> 0.4 | C9: sq ft | D9: Calculated Value | E9: 10% of built-up area
A10: Utility, plant room, parking & circulation | B10: =B5*0.3 -> 1.2 | C10: sq ft | D10: Calculated Value | E10: 30% of built-up area — HVAC, DG, STP, fire, ramps, corridors
A12: B. CONCEPTUAL FLOOR ZONING
A13: Floor | B13: Zoning
A14: Basement | B14: Utility plant rooms, STP/ETP, mortuary, stores, parking
A15: Ground Floor | B15: Main entrance & lobby, Emergency & Trauma, OPD reception, Pharmacy (retail), Diagnostics — Radiology & Lab sample collection, Billing
A16: First Floor | B16: OPD consultation suites (all specialities), Diagnostics — Lab & Imaging (CT/USG/X-ray), Physiotherapy, Dialysis unit
A17: Second Floor | B17: Operation Theatres (OT complex), ICU/HDU, CSSD, Blood storage unit, Recovery bays
A18: Third Floor | B18: IPD general wards (Medicine, Surgery), Nursing station, Patient dietary pantry
A19: Fourth Floor | B19: IPD wards (Ortho, Paediatrics), Maternity & Labour room, NICU
A20: Fifth Floor | B20: Private rooms & suites, Administrative offices, Conference/training room, Executive Health Centre
A22: This is a conceptual stacking/zoning plan for planning-stage discussion, not an architect-certified floor plan. A registered hospital architect and structural consultant must validate against final site topography, fire-NOC and HP building-bye-law requirements before construction.

Sheet 07_Bed_Mix
A1: BED MIX PLAN
A2: 100 licensed beds — launch at 75–80, scale to 100 by maturity
A3: Bed Category | B3: Launch (Yr 1) | C3: Stabilisation (Yr 3) | D3: Mature (Yr 5) | E3: % of Licensed 100 | F3: Note
A4: General Ward — Medicine/Surgery | B4: 24 | C4: 28 | D4: 30 | E4: =D4/100 -> 0.3 | F4: Multi-bed general wards, largest single category
A5: General Ward — Paediatrics | B5: 6 | C5: 7 | D5: 8 | E5: =D5/100 -> 0.08 | F5: Includes 2 isolation-capable bays
A6: Maternity & Labour | B6: 6 | C6: 7 | D6: 8 | E6: =D6/100 -> 0.08 | F6: Labour room + post-natal beds
A7: NICU | B7: 4 | C7: 5 | D7: 6 | E7: =D7/100 -> 0.06 | F7: Level II neonatal care
A8: ICU / HDU (adult) | B8: 8 | C8: 10 | D8: 12 | E8: =D8/100 -> 0.12 | F8: Critical care — ventilator-capable
A9: Semi-Private Rooms | B9: 14 | C9: 16 | D9: 18 | E9: =D9/100 -> 0.18 | F9: Twin-sharing
A10: Private Rooms & Suites | B10: 10 | C10: 11 | D10: 12 | E10: =D10/100 -> 0.12 | F10: Single occupancy incl. 2 suites
A11: Dialysis bays (non-IPD, day-care) | B11: 6 | C11: 6 | D11: 6 | E11: =D11/100 -> 0.06 | F11: Counted separately from IPD bed licence in most states; shown for capacity planning
A12: TOTAL | B12: =SUM(B4:B11) -> 78 | C12: =SUM(C4:C11) -> 90 | D12: =SUM(D4:D11) -> 100 | E12: =D12/100 -> 1
A14: Dialysis bays are shown for capacity planning but licensed-bed totals for IPD (rows above, excluding dialysis) are designed to foot to 100 at maturity — recheck this row if the mix above is edited.

Sheet 08_Department_Planning
A1: DEPARTMENT PLANNING
A2: Clinical, diagnostic and support department build-out
A3: Department | B3: Key Facilities / Equipment | C3: Phase | D3: Note
A4: OPD | B4: 16 consultation rooms across specialities, triage & vitals bay, procedure rooms | C4: Phase 1 | D4: Sized for ~350–400 patients/day at maturity
A5: Emergency & Trauma | B5: 12-bay emergency with 2 resuscitation bays, triage, minor OT, ambulance bay | C5: Phase 1 | D5: 24x7 operations from day one
A6: ICU / HDU | B6: 12 ICU + HDU beds at maturity, central monitoring, ventilators, dedicated nursing ratio 1:1 (ICU) / 1:3 (HDU) | C6: Phase 1 (8 beds) → Phase 3 (12 beds) | D6: Ratio per NABH-oriented staffing norm
A7: Operation Theatres | B7: 4 modular OTs (general, ortho, gynae, minor) at launch; +1 cardiac-capable OT in Phase 2 | C7: Phase 1 → Phase 2 | D7: Laminar air-flow in main OTs
A8: Maternity & NICU | B8: Labour room (3 tables), post-natal ward, NICU (Level II, 6 bassinets at maturity) | C8: Phase 1
A9: Diagnostics — Imaging | B9: Digital X-ray, USG, 128-slice CT (Phase 1); MRI 1.5T (Phase 2) | C9: Phase 1 → Phase 2 | D9: MRI deferred to Phase 2 pending demand validation
A10: Diagnostics — Laboratory | B10: Fully automated biochemistry & haematology, microbiology, blood bank storage/component separation | C10: Phase 1 | D10: NABL accreditation targeted alongside NABH
A11: Pharmacy | B11: In-patient pharmacy + retail OPD pharmacy, drug store with cold-chain | C11: Phase 1
A12: CSSD | B12: Centralised sterile supply, ETO + autoclave sterilisation | C12: Phase 1
A13: Blood Support | B13: Blood storage unit at launch; upgrade to licensed Blood Bank with component separation in Phase 2 | C13: Phase 1 → Phase 2 | D13: Subject to state blood-bank licensing timelines
A14: Dialysis | B14: 6 dialysis stations | C14: Phase 1
A15: Physiotherapy & Rehab | B15: Gym + electrotherapy + post-surgical rehab | C15: Phase 1
A16: Cath Lab (Cardiology) | B16: Single-plane cath lab | C16: Phase 2 | D16: Linked to Cardiology service launch
A17: Oncology Day-care | B17: 8-chair chemotherapy day-care unit | C17: Phase 2
A18: IT / MIS & HIS | B18: Hospital Information System, EMR, PACS/RIS, Power BI analytics layer, biomedical equipment integration | C18: Phase 1 (core HIS) → Phase 2 (full PACS/BI) | D18: See 21–29 Analytics sheets
A19: Facility & Support Services | B19: Housekeeping, biomedical engineering, security, dietary/kitchen, laundry, mortuary, ambulance fleet (2 at launch) | C19: Phase 1

Sheet 09_Manpower
A1: MANPOWER / HR MODEL
A2: Department-wise FTE — Launch / Stabilisation / Mature, with 15% leave-training reserve
A3: Function | B3: Role | C3: Launch Core FTE | D3: Stabilisation Core FTE | E3: Mature Core FTE | F3: Reserve Factor | G3: Launch incl. Reserve | H3: Mature incl. Reserve | I3: Note
A4: Medical | B4: Consultants (Medicine/Surgery/Ortho/Gynae/Paeds — full-time) | C4: 10 | D4: 14 | E4: 18 | F4: ='02_Assumptions'!$C$31 -> 0.15 | G4: =ROUND(C4*(1+F4),0) -> 12 | H4: =ROUND(E4*(1+F4),0) -> 21 | I4: Core specialities at launch, added in Phase 2/3
A5: Medical | B5: Consultants — Visiting/Panel (Cardiology, Nephrology, etc.) | C5: 6 | D5: 10 | E5: 16 | F5: ='02_Assumptions'!$C$31 -> 0.15 | G5: =ROUND(C5*(1+F5),0) -> 7 | H5: =ROUND(E5*(1+F5),0) -> 18 | I5: Visiting basis, converted to FTE-equivalent sessions
A6: Medical | B6: Duty Doctors / Residents (Emergency + IPD cover) | C6: 12 | D6: 16 | E6: 20 | F6: ='02_Assumptions'!$C$31 -> 0.15 | G6: =ROUND(C6*(1+F6),0) -> 14 | H6: =ROUND(E6*(1+F6),0) -> 23 | I6: 24x7 rostered cover across shifts
A7: Nursing | B7: Staff Nurses — ICU/HDU | C7: 16 | D7: 20 | E7: 24 | F7: ='02_Assumptions'!$C$31 -> 0.15 | G7: =ROUND(C7*(1+F7),0) -> 18 | H7: =ROUND(E7*(1+F7),0) -> 28 | I7: Ratio ~1:1 ICU, 1:3 HDU per shift
A8: Nursing | B8: Staff Nurses — General Ward/OPD/OT | C8: 45 | D8: 55 | E8: 68 | F8: ='02_Assumptions'!$C$31 -> 0.15 | G8: =ROUND(C8*(1+F8),0) -> 52 | H8: =ROUND(E8*(1+F8),0) -> 78 | I8: Ward ratio ~1:5–6 per shift, 3-shift rostering
A9: Nursing | B9: Nursing Supervisors / Matron | C9: 4 | D9: 5 | E9: 6 | F9: ='02_Assumptions'!$C$31 -> 0.15 | G9: =ROUND(C9*(1+F9),0) -> 5 | H9: =ROUND(E9*(1+F9),0) -> 7
A10: Allied Health | B10: Lab Technologists | C10: 8 | D10: 10 | E10: 13 | F10: ='02_Assumptions'!$C$31 -> 0.15 | G10: =ROUND(C10*(1+F10),0) -> 9 | H10: =ROUND(E10*(1+F10),0) -> 15
A11: Allied Health | B11: Radiology/Imaging Technologists | C11: 6 | D11: 8 | E11: 11 | F11: ='02_Assumptions'!$C$31 -> 0.15 | G11: =ROUND(C11*(1+F11),0) -> 7 | H11: =ROUND(E11*(1+F11),0) -> 13 | I11: Grows with MRI/Cath Lab in Phase 2
A12: Allied Health | B12: Pharmacists | C12: 6 | D12: 8 | E12: 10 | F12: ='02_Assumptions'!$C$31 -> 0.15 | G12: =ROUND(C12*(1+F12),0) -> 7 | H12: =ROUND(E12*(1+F12),0) -> 12
A13: Allied Health | B13: Physiotherapists | C13: 3 | D13: 4 | E13: 5 | F13: ='02_Assumptions'!$C$31 -> 0.15 | G13: =ROUND(C13*(1+F13),0) -> 3 | H13: =ROUND(E13*(1+F13),0) -> 6
A14: Allied Health | B14: OT Technicians / Anaesthesia Technicians | C14: 8 | D14: 10 | E14: 13 | F14: ='02_Assumptions'!$C$31 -> 0.15 | G14: =ROUND(C14*(1+F14),0) -> 9 | H14: =ROUND(E14*(1+F14),0) -> 15
A15: Allied Health | B15: Dialysis Technicians | C15: 4 | D15: 4 | E15: 5 | F15: ='02_Assumptions'!$C$31 -> 0.15 | G15: =ROUND(C15*(1+F15),0) -> 5 | H15: =ROUND(E15*(1+F15),0) -> 6
A16: Administration | B16: Hospital Administration & Front Office | C16: 10 | D16: 12 | E16: 14 | F16: ='02_Assumptions'!$C$31 -> 0.15 | G16: =ROUND(C16*(1+F16),0) -> 12 | H16: =ROUND(E16*(1+F16),0) -> 16
A17: Administration | B17: Finance & Billing | C17: 6 | D17: 8 | E17: 9 | F17: ='02_Assumptions'!$C$31 -> 0.15 | G17: =ROUND(C17*(1+F17),0) -> 7 | H17: =ROUND(E17*(1+F17),0) -> 10
A18: Administration | B18: HR & Training | C18: 3 | D18: 4 | E18: 5 | F18: ='02_Assumptions'!$C$31 -> 0.15 | G18: =ROUND(C18*(1+F18),0) -> 3 | H18: =ROUND(E18*(1+F18),0) -> 6
A19: Quality | B19: Quality/NABH Cell | C19: 2 | D19: 3 | E19: 4 | F19: ='02_Assumptions'!$C$31 -> 0.15 | G19: =ROUND(C19*(1+F19),0) -> 2 | H19: =ROUND(E19*(1+F19),0) -> 5 | I19: Drives 19_NABH_Readiness roadmap
A20: IT/MIS | B20: HIS/EMR/PACS & Biomedical IT | C20: 4 | D20: 5 | E20: 6 | F20: ='02_Assumptions'!$C$31 -> 0.15 | G20: =ROUND(C20*(1+F20),0) -> 5 | H20: =ROUND(E20*(1+F20),0) -> 7 | I20: Supports 21–29 Analytics layer
A21: Support Services | B21: Housekeeping, Security, Dietary, Laundry, Maintenance, Ambulance | C21: 40 | D21: 48 | E21: 55 | F21: ='02_Assumptions'!$C$31 -> 0.15 | G21: =ROUND(C21*(1+F21),0) -> 46 | H21: =ROUND(E21*(1+F21),0) -> 63 | I21: Largely outsourced/contract-managed FTE
A22: TOTAL FTE | C22: =SUM(C4:C21) -> 193 | D22: =SUM(D4:D21) -> 244 | E22: =SUM(E4:E21) -> 302 | G22: =SUM(G4:G21) -> 223 | H22: =SUM(H4:H21) -> 349
A24: STAFF : BED RATIO CHECK
A25: Total FTE incl. reserve, mature (Col H total) | B25: =H22 -> 349
A26: Licensed beds (mature) | B26: ='02_Assumptions'!$C$4 -> 100
A27: Staff : Bed ratio | B27: =ROUND(B25/B26,2) -> 3.49
A29: Indian private multispecialty hospitals typically run a staff:bed ratio of ~2.0x–2.8x depending on case-mix acuity and outsourcing depth; the ratio above is a sense-check, not a target to reverse-engineer headcount from.

Sheet 10_CAPEX
A1: CAPEX PLAN — BASE / LEAN / UPPER CASE
A2: All figures in ₹ Crore unless noted
A3: CAPEX Head | B3: Lean (₹40 Cr) | C3: Base (₹50 Cr) | D3: Upper (₹60 Cr) | E3: Note | F3: Share %
A4: Land & site development | B4: =$F4*'02_Assumptions'!$C$8 -> 4.8 | C4: =$F4*'02_Assumptions'!$C$7 -> 6 | D4: =$F4*'02_Assumptions'!$C$9 -> 7.2 | E4: Owned/long-lease; lower in Lean via smaller land parcel | F4: 0.12
A5: Civil construction & structure | B5: =$F5*'02_Assumptions'!$C$8 -> 15.2 | C5: =$F5*'02_Assumptions'!$C$7 -> 19 | D5: =$F5*'02_Assumptions'!$C$9 -> 22.8 | E5: Largest single head — G+5 structure | F5: 0.38
A6: MEP (electrical, HVAC, fire, plumbing) | B6: =$F6*'02_Assumptions'!$C$8 -> 4.8 | C6: =$F6*'02_Assumptions'!$C$7 -> 6 | D6: =$F6*'02_Assumptions'!$C$9 -> 7.2 | E6: Mechanical/Electrical/Plumbing infrastructure | F6: 0.12
A7: Medical equipment | B7: =$F7*'02_Assumptions'!$C$8 -> 9.6 | C7: =$F7*'02_Assumptions'!$C$7 -> 12 | D7: =$F7*'02_Assumptions'!$C$9 -> 14.4 | E7: ICU, OT, imaging (CT at launch; MRI/Cath Lab added Phase 2 outside Base Case Yr1 CAPEX) | F7: 0.24
A8: Furniture, fixtures & non-medical equipment | B8: =$F8*'02_Assumptions'!$C$8 -> 2 | C8: =$F8*'02_Assumptions'!$C$7 -> 2.5 | D8: =$F8*'02_Assumptions'!$C$9 -> 3 | E8: Beds, wards, admin, IT hardware | F8: 0.05
A9: Pre-operative expenses (licences, consultants, interest during construction) | B9: =$F9*'02_Assumptions'!$C$8 -> 2 | C9: =$F9*'02_Assumptions'!$C$7 -> 2.5 | D9: =$F9*'02_Assumptions'!$C$9 -> 3 | F9: 0.05
A10: Contingency | B10: =$F10*'02_Assumptions'!$C$8 -> 1.6 | C10: =$F10*'02_Assumptions'!$C$7 -> 2 | D10: =$F10*'02_Assumptions'!$C$9 -> 2.4 | E10: Standard project-finance contingency buffer | F10: 0.04
A11: TOTAL PROJECT CAPEX | B11: =SUM(B4:B10) -> 40 | C11: =SUM(C4:C10) -> 50 | D11: =SUM(D4:D10) -> 60 | F11: =SUM(F4:F10) -> 1
A13: FUNDING STRUCTURE (BASE CASE)
A14: Source | B14: ₹ Crore | C14: % of CAPEX
A15: Term Debt | B15: =C11*'02_Assumptions'!$C$13 -> 32.5 | C15: =B15/C11 -> 0.65
A16: Promoter Equity | B16: =C11-B15 -> 17.5 | C16: =B16/C11 -> 0.35
A18: Column F holds each head's % share of total CAPEX (Assumption-level), applied identically across Lean/Base/Upper so the mix stays consistent while only the overall envelope changes. Funding structure and debt terms link to 02_Assumptions (Debt:Equity ratio, interest rate, tenure) and drive 14_Cash_Flow.

Sheet 11_OPEX
A1: OPEX MODEL — BASE CASE (₹ LAKH)
A2: 10-year operating cost build-up
B3: Yr 1 | C3: Yr 2 | D3: Yr 3 | E3: Yr 4 | F3: Yr 5 | G3: Yr 6 | H3: Yr 7 | I3: Yr 8 | J3: Yr 9 | K3: Yr 10
A4: Staff Cost (₹ Lakh) | B4: =ROUND(B15*B16,1) -> 1338 | C4: =ROUND(C15*C16,1) -> 1649.2 | D4: =ROUND(D15*D16,1) -> 2001.5 | E4: =ROUND(E15*E16,1) -> 2399.8 | F4: =ROUND(F15*F16,1) -> 2848.9 | G4: =ROUND(G15*G16,1) -> 3076.8 | H4: =ROUND(H15*H16,1) -> 3322.9 | I4: =ROUND(I15*I16,1) -> 3588.7 | ... K4: =ROUND(K15*K16,1) -> 4185.9
A5: Consumables, Drugs & Surgical Items (₹ Lakh) | B5: =ROUND('12_Revenue'!B12*0.22,1) -> 382.9 | C5: =ROUND(B5*(1+'02_Assumptions'!$C$25),1) -> 405.9 | D5: =ROUND(C5*(1+'02_Assumptions'!$C$25),1) -> 430.3 | E5: =ROUND(D5*(1+'02_Assumptions'!$C$25),1) -> 456.1 | F5: =ROUND(E5*(1+'02_Assumptions'!$C$25),1) -> 483.5 | G5: =ROUND(F5*(1+'02_Assumptions'!$C$25),1) -> 512.5 | H5: =ROUND(G5*(1+'02_Assumptions'!$C$25),1) -> 543.3 | I5: =ROUND(H5*(1+'02_Assumptions'!$C$25),1) -> 575.9 | J5: =ROUND(I5*(1+'02_Assumptions'!$C$25),1) -> 610.5 | K5: =ROUND(J5*(1+'02_Assumptions'!$C$25),1) -> 647.1
A6: Equipment AMC/CMC & Maintenance (₹ Lakh) | B6: =ROUND('12_Revenue'!B12*0.04,1) -> 69.6 | C6: =ROUND(B6*(1+'02_Assumptions'!$C$25),1) -> 73.8 | D6: =ROUND(C6*(1+'02_Assumptions'!$C$25),1) -> 78.2 | E6: =ROUND(D6*(1+'02_Assumptions'!$C$25),1) -> 82.9 | F6: =ROUND(E6*(1+'02_Assumptions'!$C$25),1) -> 87.9 | G6: =ROUND(F6*(1+'02_Assumptions'!$C$25),1) -> 93.2 | H6: =ROUND(G6*(1+'02_Assumptions'!$C$25),1) -> 98.8 | I6: =ROUND(H6*(1+'02_Assumptions'!$C$25),1) -> 104.7 | J6: =ROUND(I6*(1+'02_Assumptions'!$C$25),1) -> 111 | K6: =ROUND(J6*(1+'02_Assumptions'!$C$25),1) -> 117.7
A7: Utilities (Power, Water, Fuel) (₹ Lakh) | B7: =ROUND('12_Revenue'!B12*0.035,1) -> 60.9 | C7: =ROUND(B7*(1+'02_Assumptions'!$C$25),1) -> 64.6 | D7: =ROUND(C7*(1+'02_Assumptions'!$C$25),1) -> 68.5 | E7: =ROUND(D7*(1+'02_Assumptions'!$C$25),1) -> 72.6 | F7: =ROUND(E7*(1+'02_Assumptions'!$C$25),1) -> 77 | G7: =ROUND(F7*(1+'02_Assumptions'!$C$25),1) -> 81.6 | H7: =ROUND(G7*(1+'02_Assumptions'!$C$25),1) -> 86.5 | I7: =ROUND(H7*(1+'02_Assumptions'!$C$25),1) -> 91.7 | J7: =ROUND(I7*(1+'02_Assumptions'!$C$25),1) -> 97.2 | K7: =ROUND(J7*(1+'02_Assumptions'!$C$25),1) -> 103
A8: Marketing & Referral Development (₹ Lakh) | B8: =ROUND('12_Revenue'!B12*0.025,1) -> 43.5 | C8: =ROUND(B8*(1+'02_Assumptions'!$C$25),1) -> 46.1 | D8: =ROUND(C8*(1+'02_Assumptions'!$C$25),1) -> 48.9 | E8: =ROUND(D8*(1+'02_Assumptions'!$C$25),1) -> 51.8 | F8: =ROUND(E8*(1+'02_Assumptions'!$C$25),1) -> 54.9 | G8: =ROUND(F8*(1+'02_Assumptions'!$C$25),1) -> 58.2 | H8: =ROUND(G8*(1+'02_Assumptions'!$C$25),1) -> 61.7 | I8: =ROUND(H8*(1+'02_Assumptions'!$C$25),1) -> 65.4 | J8: =ROUND(I8*(1+'02_Assumptions'!$C$25),1) -> 69.3 | K8: =ROUND(J8*(1+'02_Assumptions'!$C$25),1) -> 73.5
A9: Admin, Insurance & Other Overheads (₹ Lakh) | B9: =ROUND('12_Revenue'!B12*0.05,1) -> 87 | C9: =ROUND(B9*(1+'02_Assumptions'!$C$25),1) -> 92.2 | D9: =ROUND(C9*(1+'02_Assumptions'!$C$25),1) -> 97.7 | E9: =ROUND(D9*(1+'02_Assumptions'!$C$25),1) -> 103.6 | F9: =ROUND(E9*(1+'02_Assumptions'!$C$25),1) -> 109.8 | G9: =ROUND(F9*(1+'02_Assumptions'!$C$25),1) -> 116.4 | H9: =ROUND(G9*(1+'02_Assumptions'!$C$25),1) -> 123.4 | I9: =ROUND(H9*(1+'02_Assumptions'!$C$25),1) -> 130.8 | J9: =ROUND(I9*(1+'02_Assumptions'!$C$25),1) -> 138.6 | K9: =ROUND(J9*(1+'02_Assumptions'!$C$25),1) -> 146.9
A10: TOTAL OPEX (₹ Lakh) | B10: =B4+B5+B6+B7+B8+B9 -> 1981.9 | C10: =C4+C5+C6+C7+C8+C9 -> 2331.8 | D10: =D4+D5+D6+D7+D8+D9 -> 2725.1 | E10: =E4+E5+E6+E7+E8+E9 -> 3166.8 | F10: =F4+F5+F6+F7+F8+F9 -> 3662 | G10: =G4+G5+G6+G7+G8+G9 -> 3938.7 | H10: =H4+H5+H6+H7+H8+H9 -> 4236.6 | I10: =I4+I5+I6+I7+I8+I9 -> 4557.2 | ... K10: =K4+K5+K6+K7+K8+K9 -> 5274.1
A11: EBITDA (₹ Lakh) | B11: ='12_Revenue'!B12-B10 -> -241.4 | C11: ='12_Revenue'!C12-C10 -> 19.6 | D11: ='12_Revenue'!D12-D10 -> 356.4 | E11: ='12_Revenue'!E12-E10 -> 600.5 | F11: ='12_Revenue'!F12-F10 -> 899.2 | G11: ='12_Revenue'!G12-G10 -> 896.2 | H11: ='12_Revenue'!H12-H10 -> 888.4 | I11: ='12_Revenue'!I12-I10 -> 875.3 | ... K11: ='12_Revenue'!K12-K10 -> 829.8
A12: EBITDA Margin % | B12: =B11/'12_Revenue'!B12 -> -0.13869578 | C12: =C11/'12_Revenue'!C12 -> 0.0083354597 | D12: =D11/'12_Revenue'!D12 -> 0.11565796 | E12: =E11/'12_Revenue'!E12 -> 0.15939798 | F12: =F11/'12_Revenue'!F12 -> 0.1971411 | G12: =G11/'12_Revenue'!G12 -> 0.18536061 | H12: =H11/'12_Revenue'!H12 -> 0.17334634 | I12: =I11/'12_Revenue'!I12 -> 0.16112287 | ... K12: =K11/'12_Revenue'!K12 -> 0.13594587
A14: Staff cost is FTE (from 09_Manpower, ramping launch→mature) × a Benchmark blended cost/FTE of ₹6.0 Lakh p.a. in Year 1, escalated by the staff increment assumption. Non-staff OPEX heads are set as a Year-1 % of Net Revenue (Benchmark ratios for a Tier-2/3 100-bed hospital) and then inflated — all editable in 02_Assumptions.
A15: Total FTE incl. reserve | B15: ='09_Manpower'!$G$22 -> 223 | C15: =MIN('09_Manpower'!$G$22+('09_Manpower'!$H$22-'09_Manpower'!$G$22)/4*(2-1),'09_Manpower'!$H$22) -> 254.5 | D15: =MIN('09_Manpower'!$G$22+('09_Manpower'!$H$22-'09_Manpower'!$G$22)/4*(3-1),'09_Manpower'!$H$22) -> 286 | E15: =MIN('09_Manpower'!$G$22+('09_Manpower'!$H$22-'09_Manpower'!$G$22)/4*(4-1),'09_Manpower'!$H$22) -> 317.5 | F15: =MIN('09_Manpower'!$G$22+('09_Manpower'!$H$22-'09_Manpower'!$G$22)/4*(5-1),'09_Manpower'!$H$22) -> 349 | G15: =MIN('09_Manpower'!$G$22+('09_Manpower'!$H$22-'09_Manpower'!$G$22)/4*(6-1),'09_Manpower'!$H$22) -> 349 | H15: =MIN('09_Manpower'!$G$22+('09_Manpower'!$H$22-'09_Manpower'!$G$22)/4*(7-1),'09_Manpower'!$H$22) -> 349 | I15: =MIN('09_Manpower'!$G$22+('09_Manpower'!$H$22-'09_Manpower'!$G$22)/4*(8-1),'09_Manpower'!$H$22) -> 349 | J15: =MIN('09_Manpower'!$G$22+('09_Manpower'!$H$22-'09_Manpower'!$G$22)/4*(9-1),'09_Manpower'!$H$22) -> 349 | K15: =MIN('09_Manpower'!$G$22+('09_Manpower'!$H$22-'09_Manpower'!$G$22)/4*(10-1),'09_Manpower'!$H$22) -> 349
A16: Blended Cost per FTE (₹ Lakh p.a.) | B16: =6 -> 6 | C16: =B16*(1+'02_Assumptions'!$C$26) -> 6.48 | D16: =C16*(1+'02_Assumptions'!$C$26) -> 6.9984 | E16: =D16*(1+'02_Assumptions'!$C$26) -> 7.558272 | F16: =E16*(1+'02_Assumptions'!$C$26) -> 8.1629338 | G16: =F16*(1+'02_Assumptions'!$C$26) -> 8.8159685 | H16: =G16*(1+'02_Assumptions'!$C$26) -> 9.5212459 | I16: =H16*(1+'02_Assumptions'!$C$26) -> 10.282946 | J16: =I16*(1+'02_Assumptions'!$C$26) -> 11.105581 | K16: =J16*(1+'02_Assumptions'!$C$26) -> 11.994028

Sheet 12_Revenue
A1: REVENUE MODEL — BASE CASE (₹ LAKH)
A2: 10-year build-up, Year 1 = launch year
B3: Yr 1 | C3: Yr 2 | D3: Yr 3 | E3: Yr 4 | F3: Yr 5 | G3: Yr 6 | H3: Yr 7 | I3: Yr 8 | J3: Yr 9 | K3: Yr 10
A4: Operational Beds | B4: ='02_Assumptions'!$C$5 -> 78 | C4: =MIN('02_Assumptions'!$C$5+('02_Assumptions'!$C$6-'02_Assumptions'!$C$5)/4*(2-1),'02_Assumptions'!$C$6) -> 83.5 | D4: =MIN('02_Assumptions'!$C$5+('02_Assumptions'!$C$6-'02_Assumptions'!$C$5)/4*(3-1),'02_Assumptions'!$C$6) -> 89 | E4: =MIN('02_Assumptions'!$C$5+('02_Assumptions'!$C$6-'02_Assumptions'!$C$5)/4*(4-1),'02_Assumptions'!$C$6) -> 94.5 | F4: =MIN('02_Assumptions'!$C$5+('02_Assumptions'!$C$6-'02_Assumptions'!$C$5)/4*(5-1),'02_Assumptions'!$C$6) -> 100 | G4: =MIN('02_Assumptions'!$C$5+('02_Assumptions'!$C$6-'02_Assumptions'!$C$5)/4*(6-1),'02_Assumptions'!$C$6) -> 100 | H4: =MIN('02_Assumptions'!$C$5+('02_Assumptions'!$C$6-'02_Assumptions'!$C$5)/4*(7-1),'02_Assumptions'!$C$6) -> 100 | I4: =MIN('02_Assumptions'!$C$5+('02_Assumptions'!$C$6-'02_Assumptions'!$C$5)/4*(8-1),'02_Assumptions'!$C$6) -> 100 | J4: =MIN('02_Assumptions'!$C$5+('02_Assumptions'!$C$6-'02_Assumptions'!$C$5)/4*(9-1),'02_Assumptions'!$C$6) -> 100 | K4: =MIN('02_Assumptions'!$C$5+('02_Assumptions'!$C$6-'02_Assumptions'!$C$5)/4*(10-1),'02_Assumptions'!$C$6) -> 100
A5: Occupancy % | B5: ='02_Assumptions'!$C$18 -> 0.42 | C5: ='02_Assumptions'!$C$18+('02_Assumptions'!$C$19-'02_Assumptions'!$C$18)/2*(2-1) -> 0.5 | D5: ='02_Assumptions'!$C$18+('02_Assumptions'!$C$19-'02_Assumptions'!$C$18)/2*(3-1) -> 0.58 | E5: ='02_Assumptions'!$C$19+('02_Assumptions'!$C$20-'02_Assumptions'!$C$19)/2*(4-3) -> 0.63 | F5: ='02_Assumptions'!$C$19+('02_Assumptions'!$C$20-'02_Assumptions'!$C$19)/2*(5-3) -> 0.68 | G5: ='02_Assumptions'!$C$20 -> 0.68 | H5: ='02_Assumptions'!$C$20 -> 0.68 | I5: ='02_Assumptions'!$C$20 -> 0.68 | J5: ='02_Assumptions'!$C$20 -> 0.68 | K5: ='02_Assumptions'!$C$20 -> 0.68
A6: Patient Days | B6: =ROUND(B4*B5*365,0) -> 11957 | C6: =ROUND(C4*C5*365,0) -> 15239 | D6: =ROUND(D4*D5*365,0) -> 18841 | E6: =ROUND(E4*E5*365,0) -> 21730 | F6: =ROUND(F4*F5*365,0) -> 24820 | G6: =ROUND(G4*G5*365,0) -> 24820 | H6: =ROUND(H4*H5*365,0) -> 24820 | I6: =ROUND(I4*I5*365,0) -> 24820 | ... K6: =ROUND(K4*K5*365,0) -> 24820
A7: ARPOBD (₹, blended IPD rate/occupied-bed-day) | B7: =9500 -> 9500 | C7: =B7*(1+'02_Assumptions'!$C$24) -> 10070 | D7: =C7*(1+'02_Assumptions'!$C$24) -> 10674.2 | E7: =D7*(1+'02_Assumptions'!$C$24) -> 11314.652 | F7: =E7*(1+'02_Assumptions'!$C$24) -> 11993.531 | G7: =F7*(1+'02_Assumptions'!$C$24) -> 12713.143 | H7: =G7*(1+'02_Assumptions'!$C$24) -> 13475.932 | I7: =H7*(1+'02_Assumptions'!$C$24) -> 14284.487 | J7: =I7*(1+'02_Assumptions'!$C$24) -> 15141.557 | K7: =J7*(1+'02_Assumptions'!$C$24) -> 16050.05
A8: Gross IPD Revenue (₹ Lakh) | B8: =ROUND(B6*B7/100000,1) -> 1135.9 | C8: =ROUND(C6*C7/100000,1) -> 1534.6 | D8: =ROUND(D6*D7/100000,1) -> 2011.1 | E8: =ROUND(E6*E7/100000,1) -> 2458.7 | F8: =ROUND(F6*F7/100000,1) -> 2976.8 | G8: =ROUND(G6*G7/100000,1) -> 3155.4 | H8: =ROUND(H6*H7/100000,1) -> 3344.7 | I8: =ROUND(I6*I7/100000,1) -> 3545.4 | ... K8: =ROUND(K6*K7/100000,1) -> 3983.6
A9: Gross Total Revenue (₹ Lakh) | B9: =ROUND(B8/'02_Assumptions'!$C$22,1) -> 1832.1 | C9: =ROUND(C8/'02_Assumptions'!$C$22,1) -> 2475.2 | D9: =ROUND(D8/'02_Assumptions'!$C$22,1) -> 3243.7 | E9: =ROUND(E8/'02_Assumptions'!$C$22,1) -> 3965.6 | F9: =ROUND(F8/'02_Assumptions'!$C$22,1) -> 4801.3 | G9: =ROUND(G8/'02_Assumptions'!$C$22,1) -> 5089.4 | H9: =ROUND(H8/'02_Assumptions'!$C$22,1) -> 5394.7 | I9: =ROUND(I8/'02_Assumptions'!$C$22,1) -> 5718.4 | ... K9: =ROUND(K8/'02_Assumptions'!$C$22,1) -> 6425.2
A10: Gross OPD+Diagnostics+Pharmacy Revenue (₹ Lakh) | B10: =B9-B8 -> 696.2 | C10: =C9-C8 -> 940.6 | D10: =D9-D8 -> 1232.6 | E10: =E9-E8 -> 1506.9 | F10: =F9-F8 -> 1824.5 | G10: =G9-G8 -> 1934 | H10: =H9-H8 -> 2050 | I10: =I9-I8 -> 2173 | ... K10: =K9-K8 -> 2441.6
A11: Less: Bad Debt / Discount / TPA Deduction (₹ Lakh) | B11: =ROUND(B9*'02_Assumptions'!$C$27,1) -> 91.6 | C11: =ROUND(C9*'02_Assumptions'!$C$27,1) -> 123.8 | D11: =ROUND(D9*'02_Assumptions'!$C$27,1) -> 162.2 | E11: =ROUND(E9*'02_Assumptions'!$C$27,1) -> 198.3 | F11: =ROUND(F9*'02_Assumptions'!$C$27,1) -> 240.1 | G11: =ROUND(G9*'02_Assumptions'!$C$27,1) -> 254.5 | H11: =ROUND(H9*'02_Assumptions'!$C$27,1) -> 269.7 | I11: =ROUND(I9*'02_Assumptions'!$C$27,1) -> 285.9 | ... K11: =ROUND(K9*'02_Assumptions'!$C$27,1) -> 321.3
A12: NET REVENUE (₹ Lakh) | B12: =B9-B11 -> 1740.5 | C12: =C9-C11 -> 2351.4 | D12: =D9-D11 -> 3081.5 | E12: =E9-E11 -> 3767.3 | F12: =F9-F11 -> 4561.2 | G12: =G9-G11 -> 4834.9 | H12: =H9-H11 -> 5125 | I12: =I9-I11 -> 5432.5 | ... K12: =K9-K11 -> 6103.9
A14: ARPOBD (₹9,500/occupied-bed-day, Year 1) is a Benchmark for a Tier-2/3 100-bed private multispecialty hospital, blending room rent, OT, ICU, nursing and consumable mark-up; it is not any specific hospital's actual tariff card. Occupancy and bed ramp-up are linked live to 02_Assumptions.

Sheet 13_PL
A1: PROFIT & LOSS STATEMENT — BASE CASE (₹ LAKH)
A2: 10-year projection
B3: Yr 1 | C3: Yr 2 | D3: Yr 3 | E3: Yr 4 | F3: Yr 5 | G3: Yr 6 | H3: Yr 7 | I3: Yr 8 | J3: Yr 9 | K3: Yr 10
A4: Net Revenue (₹ Lakh) | B4: ='12_Revenue'!B12 -> 1740.5 | C4: ='12_Revenue'!C12 -> 2351.4 | D4: ='12_Revenue'!D12 -> 3081.5 | E4: ='12_Revenue'!E12 -> 3767.3 | F4: ='12_Revenue'!F12 -> 4561.2 | G4: ='12_Revenue'!G12 -> 4834.9 | H4: ='12_Revenue'!H12 -> 5125 | I4: ='12_Revenue'!I12 -> 5432.5 | ... K4: ='12_Revenue'!K12 -> 6103.9
A5: Total OPEX (₹ Lakh) | B5: ='11_OPEX'!B10 -> 1981.9 | C5: ='11_OPEX'!C10 -> 2331.8 | D5: ='11_OPEX'!D10 -> 2725.1 | E5: ='11_OPEX'!E10 -> 3166.8 | F5: ='11_OPEX'!F10 -> 3662 | G5: ='11_OPEX'!G10 -> 3938.7 | H5: ='11_OPEX'!H10 -> 4236.6 | I5: ='11_OPEX'!I10 -> 4557.2 | ... K5: ='11_OPEX'!K10 -> 5274.1
A6: EBITDA (₹ Lakh) | B6: =B4-B5 -> -241.4 | C6: =C4-C5 -> 19.6 | D6: =D4-D5 -> 356.4 | E6: =E4-E5 -> 600.5 | F6: =F4-F5 -> 899.2 | G6: =G4-G5 -> 896.2 | H6: =H4-H5 -> 888.4 | I6: =I4-I5 -> 875.3 | ... K6: =K4-K5 -> 829.8
A7: Depreciation (₹ Lakh) | B7: =ROUND('10_CAPEX'!$C$11*100*0.62*'02_Assumptions'!$C$28+'10_CAPEX'!$C$11*100*0.29*'02_Assumptions'!$C$29,1) -> 238 | C7: =ROUND('10_CAPEX'!$C$11*100*0.62*'02_Assumptions'!$C$28+'10_CAPEX'!$C$11*100*0.29*'02_Assumptions'!$C$29,1) -> 238 | D7: =ROUND('10_CAPEX'!$C$11*100*0.62*'02_Assumptions'!$C$28+'10_CAPEX'!$C$11*100*0.29*'02_Assumptions'!$C$29,1) -> 238 | E7: =ROUND('10_CAPEX'!$C$11*100*0.62*'02_Assumptions'!$C$28+'10_CAPEX'!$C$11*100*0.29*'02_Assumptions'!$C$29,1) -> 238 | F7: =ROUND('10_CAPEX'!$C$11*100*0.62*'02_Assumptions'!$C$28+'10_CAPEX'!$C$11*100*0.29*'02_Assumptions'!$C$29,1) -> 238 | G7: =ROUND('10_CAPEX'!$C$11*100*0.62*'02_Assumptions'!$C$28+'10_CAPEX'!$C$11*100*0.29*'02_Assumptions'!$C$29,1) -> 238 | H7: =ROUND('10_CAPEX'!$C$11*100*0.62*'02_Assumptions'!$C$28+'10_CAPEX'!$C$11*100*0.29*'02_Assumptions'!$C$29,1) -> 238 | I7: =ROUND('10_CAPEX'!$C$11*100*0.62*'02_Assumptions'!$C$28+'10_CAPEX'!$C$11*100*0.29*'02_Assumptions'!$C$29,1) -> 238 | ... K7: =ROUND('10_CAPEX'!$C$11*100*0.62*'02_Assumptions'!$C$28+'10_CAPEX'!$C$11*100*0.29*'02_Assumptions'!$C$29,1) -> 238
A8: EBIT (₹ Lakh) | B8: =B6-B7 -> -479.4 | C8: =C6-C7 -> -218.4 | D8: =D6-D7 -> 118.4 | E8: =E6-E7 -> 362.5 | F8: =F6-F7 -> 661.2 | G8: =G6-G7 -> 658.2 | H8: =H6-H7 -> 650.4 | I8: =I6-I7 -> 637.3 | ... K8: =K6-K7 -> 591.8
A9: Interest on Term Loan (₹ Lakh) | B9: =IF(1<='02_Assumptions'!$C$15,MAX('10_CAPEX'!$B$15*100-('10_CAPEX'!$B$15*100/'02_Assumptions'!$C$15)*(1-1),0)*'02_Assumptions'!$C$14,0) -> 341.25 | C9: =IF(2<='02_Assumptions'!$C$15,MAX('10_CAPEX'!$B$15*100-('10_CAPEX'!$B$15*100/'02_Assumptions'!$C$15)*(2-1),0)*'02_Assumptions'!$C$14,0) -> 307.125 | D9: =IF(3<='02_Assumptions'!$C$15,MAX('10_CAPEX'!$B$15*100-('10_CAPEX'!$B$15*100/'02_Assumptions'!$C$15)*(3-1),0)*'02_Assumptions'!$C$14,0) -> 273 | E9: =IF(4<='02_Assumptions'!$C$15,MAX('10_CAPEX'!$B$15*100-('10_CAPEX'!$B$15*100/'02_Assumptions'!$C$15)*(4-1),0)*'02_Assumptions'!$C$14,0) -> 238.875 | F9: =IF(5<='02_Assumptions'!$C$15,MAX('10_CAPEX'!$B$15*100-('10_CAPEX'!$B$15*100/'02_Assumptions'!$C$15)*(5-1),0)*'02_Assumptions'!$C$14,0) -> 204.75 | G9: =IF(6<='02_Assumptions'!$C$15,MAX('10_CAPEX'!$B$15*100-('10_CAPEX'!$B$15*100/'02_Assumptions'!$C$15)*(6-1),0)*'02_Assumptions'!$C$14,0) -> 170.625 | H9: =IF(7<='02_Assumptions'!$C$15,MAX('10_CAPEX'!$B$15*100-('10_CAPEX'!$B$15*100/'02_Assumptions'!$C$15)*(7-1),0)*'02_Assumptions'!$C$14,0) -> 136.5 | I9: =IF(8<='02_Assumptions'!$C$15,MAX('10_CAPEX'!$B$15*100-('10_CAPEX'!$B$15*100/'02_Assumptions'!$C$15)*(8-1),0)*'02_Assumptions'!$C$14,0) -> 102.375 | J9: =IF(9<='02_Assumptions'!$C$15,MAX('10_CAPEX'!$B$15*100-('10_CAPEX'!$B$15*100/'02_Assumptions'!$C$15)*(9-1),0)*'02_Assumptions'!$C$14,0) -> 68.25 | K9: =IF(10<='02_Assumptions'!$C$15,MAX('10_CAPEX'!$B$15*100-('10_CAPEX'!$B$15*100/'02_Assumptions'!$C$15)*(10-1),0)*'02_Assumptions'!$C$14,0) -> 34.125
A10: PBT (₹ Lakh) | B10: =B8-B9 -> -820.65 | C10: =C8-C9 -> -525.525 | D10: =D8-D9 -> -154.6 | E10: =E8-E9 -> 123.625 | F10: =F8-F9 -> 456.45 | G10: =G8-G9 -> 487.575 | H10: =H8-H9 -> 513.9 | I10: =I8-I9 -> 534.925 | ... K10: =K8-K9 -> 557.675
A11: Tax (₹ Lakh) | B11: =MAX(B10,0)*'02_Assumptions'!$C$30 -> 0 | C11: =MAX(C10,0)*'02_Assumptions'!$C$30 -> 0 | D11: =MAX(D10,0)*'02_Assumptions'!$C$30 -> 0 | E11: =MAX(E10,0)*'02_Assumptions'!$C$30 -> 30.90625 | F11: =MAX(F10,0)*'02_Assumptions'!$C$30 -> 114.1125 | G11: =MAX(G10,0)*'02_Assumptions'!$C$30 -> 121.89375 | H11: =MAX(H10,0)*'02_Assumptions'!$C$30 -> 128.475 | I11: =MAX(I10,0)*'02_Assumptions'!$C$30 -> 133.73125 | ... K11: =MAX(K10,0)*'02_Assumptions'!$C$30 -> 139.41875
A12: PAT (₹ Lakh) | B12: =B10-B11 -> -820.65 | C12: =C10-C11 -> -525.525 | D12: =D10-D11 -> -154.6 | E12: =E10-E11 -> 92.71875 | F12: =F10-F11 -> 342.3375 | G12: =G10-G11 -> 365.68125 | H12: =H10-H11 -> 385.425 | I12: =I10-I11 -> 401.19375 | ... K12: =K10-K11 -> 418.25625
A13: PAT Margin % | B13: =B12/B4 -> -0.47150244 | C13: =C12/C4 -> -0.22349451 | D13: =D12/D4 -> -0.050170372 | E13: =E12/E4 -> 0.024611459 | F13: =F12/F4 -> 0.075054262 | G13: =G12/G4 -> 0.075633674 | H13: =H12/H4 -> 0.075204878 | I13: =I12/I4 -> 0.073850667 | ... K13: =K12/K4 -> 0.068522789
A15: Depreciation is straight-line on the Building+MEP share (62% of CAPEX) at the building rate, and the Medical Equipment+FF&E share (29% of CAPEX) at the equipment rate — both from 02_Assumptions. Interest assumes equal annual principal repayment (reducing balance) over the loan tenure; Year 1 interest is highest and tapers to zero once the loan is repaid.

Sheet 14_Cash_Flow
A1: CASH FLOW & DEBT SERVICE — BASE CASE (₹ LAKH)
A2: Year 0 = CAPEX deployment; Year 1–10 = operations
B3: Yr 0 | C3: Yr 1 | D3: Yr 2 | E3: Yr 3 | F3: Yr 4 | G3: Yr 5 | H3: Yr 6 | I3: Yr 7 | J3: Yr 8 | K3: Yr 9 | L3: Yr 10
A5: CAPEX Outflow (₹ Lakh) | B5: =-'10_CAPEX'!$C$11*100 -> -5000 | C5: 0 | D5: 0 | E5: 0 | F5: 0 | G5: 0 | H5: 0 | I5: 0 | J5: 0 | K5: 0 | L5: 0
A6: Debt Drawdown (₹ Lakh) | B6: ='10_CAPEX'!$B$15*100 -> 3250 | C6: 0 | D6: 0 | E6: 0 | F6: 0 | G6: 0 | H6: 0 | I6: 0 | J6: 0 | K6: 0 | L6: 0
A7: Equity Infusion (₹ Lakh) | B7: ='10_CAPEX'!$B$16*100 -> 1750 | C7: 0 | D7: 0 | E7: 0 | F7: 0 | G7: 0 | H7: 0 | I7: 0 | J7: 0 | K7: 0 | L7: 0
A8: PAT (₹ Lakh) | B8: 0 | C8: ='13_PL'!B12 -> -820.65 | D8: ='13_PL'!C12 -> -525.525 | E8: ='13_PL'!D12 -> -154.6 | F8: ='13_PL'!E12 -> 92.71875 | G8: ='13_PL'!F12 -> 342.3375 | H8: ='13_PL'!G12 -> 365.68125 | I8: ='13_PL'!H12 -> 385.425 | J8: ='13_PL'!I12 -> 401.19375 | ... L8: ='13_PL'!K12 -> 418.25625
A9: Add: Depreciation (₹ Lakh) | B9: 0 | C9: ='13_PL'!B7 -> 238 | D9: ='13_PL'!C7 -> 238 | E9: ='13_PL'!D7 -> 238 | F9: ='13_PL'!E7 -> 238 | G9: ='13_PL'!F7 -> 238 | H9: ='13_PL'!G7 -> 238 | I9: ='13_PL'!H7 -> 238 | J9: ='13_PL'!I7 -> 238 | ... L9: ='13_PL'!K7 -> 238
A10: Less: Principal Repayment (₹ Lakh) | B10: 0 | C10: =-(IF(1<='02_Assumptions'!$C$15,'10_CAPEX'!$B$15*100/'02_Assumptions'!$C$15,0)) -> -325 | D10: =-(IF(2<='02_Assumptions'!$C$15,'10_CAPEX'!$B$15*100/'02_Assumptions'!$C$15,0)) -> -325 | E10: =-(IF(3<='02_Assumptions'!$C$15,'10_CAPEX'!$B$15*100/'02_Assumptions'!$C$15,0)) -> -325 | F10: =-(IF(4<='02_Assumptions'!$C$15,'10_CAPEX'!$B$15*100/'02_Assumptions'!$C$15,0)) -> -325 | G10: =-(IF(5<='02_Assumptions'!$C$15,'10_CAPEX'!$B$15*100/'02_Assumptions'!$C$15,0)) -> -325 | H10: =-(IF(6<='02_Assumptions'!$C$15,'10_CAPEX'!$B$15*100/'02_Assumptions'!$C$15,0)) -> -325 | I10: =-(IF(7<='02_Assumptions'!$C$15,'10_CAPEX'!$B$15*100/'02_Assumptions'!$C$15,0)) -> -325 | J10: =-(IF(8<='02_Assumptions'!$C$15,'10_CAPEX'!$B$15*100/'02_Assumptions'!$C$15,0)) -> -325 | K10: =-(IF(9<='02_Assumptions'!$C$15,'10_CAPEX'!$B$15*100/'02_Assumptions'!$C$15,0)) -> -325 | L10: =-(IF(10<='02_Assumptions'!$C$15,'10_CAPEX'!$B$15*100/'02_Assumptions'!$C$15,0)) -> -325
A11: Net Cash Flow (₹ Lakh) | B11: =SUM(B5:B10) -> 0 | C11: =SUM(C8:C10) -> -907.65 | D11: =SUM(D8:D10) -> -612.525 | E11: =SUM(E8:E10) -> -241.6 | F11: =SUM(F8:F10) -> 5.71875 | G11: =SUM(G8:G10) -> 255.3375 | H11: =SUM(H8:H10) -> 278.68125 | I11: =SUM(I8:I10) -> 298.425 | J11: =SUM(J8:J10) -> 314.19375 | ... L11: =SUM(L8:L10) -> 331.25625
A12: Cumulative Cash Flow (₹ Lakh) | B12: =B11 -> 0 | C12: =B12+C11 -> -907.65 | D12: =C12+D11 -> -1520.175 | E12: =D12+E11 -> -1761.775 | F12: =E12+F11 -> -1756.0563 | G12: =F12+G11 -> -1500.7188 | H12: =G12+H11 -> -1222.0375 | I12: =H12+I11 -> -923.6125 | J12: =I12+J11 -> -609.41875 | ... L12: =K12+L11 -> 47.15
A13: DSCR (Debt Service Coverage Ratio) | B13: n/a | C13: =IF(-C10+'13_PL'!B9=0,"n/a",(C8+C9+'13_PL'!B9)/(-C10+'13_PL'!B9)) -> -0.36232645 | D13: =IF(-D10+'13_PL'!C9=0,"n/a",(D8+D9+'13_PL'!C9)/(-D10+'13_PL'!C9)) -> 0.031006526 | E13: =IF(-E10+'13_PL'!D9=0,"n/a",(E8+E9+'13_PL'!D9)/(-E10+'13_PL'!D9)) -> 0.59598662 | F13: =IF(-F10+'13_PL'!E9=0,"n/a",(F8+F9+'13_PL'!E9)/(-F10+'13_PL'!E9)) -> 1.0101419 | G13: =IF(-G10+'13_PL'!F9=0,"n/a",(G8+G9+'13_PL'!F9)/(-G10+'13_PL'!F9)) -> 1.4819962 | H13: =IF(-H10+'13_PL'!G9=0,"n/a",(H8+H9+'13_PL'!G9)/(-H10+'13_PL'!G9)) -> 1.5622825 | I13: =IF(-I10+'13_PL'!H9=0,"n/a",(I8+I9+'13_PL'!H9)/(-I10+'13_PL'!H9)) -> 1.6466414 | J13: =IF(-J10+'13_PL'!I9=0,"n/a",(J8+J9+'13_PL'!I9)/(-J10+'13_PL'!I9)) -> 1.7351711 | ... L13: =IF(-L10+'13_PL'!K9=0,"n/a",(L8+L9+'13_PL'!K9)/(-L10+'13_PL'!K9)) -> 1.9223982
A15: DSCR = (PAT + Depreciation + Interest) ÷ (Principal + Interest) for that year. Lenders for hospital infrastructure projects typically look for an average DSCR of 1.4x–1.8x across the loan tenure; treat any year below ~1.2x as a flag for renegotiating tenure or phasing CAPEX further.

Sheet 15_Break_Even
A1: BREAK-EVEN ANALYSIS — MATURE YEAR (YEAR 5)
A2: Contribution-margin based break-even, ₹ Lakh
A3: Metric | B3: Value | C3: Note
A4: Net Revenue, Year 5 (₹ Lakh) | B4: ='12_Revenue'!F12 -> 4561.2 | C4: Link
A5: Variable Cost, Year 5 — Consumables+Utilities+Marketing (₹ Lakh) | B5: ='11_OPEX'!F5+'11_OPEX'!F7+'11_OPEX'!F8 -> 615.4 | C5: Treated as volume-variable
A6: Fixed Cost, Year 5 — Staff+AMC+Admin (₹ Lakh) | B6: ='11_OPEX'!F4+'11_OPEX'!F6+'11_OPEX'!F9 -> 3046.6 | C6: Treated as largely fixed in the short run
A7: Contribution Margin % (of Net Revenue) | B7: =(B4-B5)/B4 -> 0.86507937 | C7: Calculated
A8: Break-Even Net Revenue (₹ Lakh) | B8: =B6/B7 -> 3521.7578 | C8: Fixed Cost ÷ Contribution Margin %
A9: Actual Net Revenue, Year 5 (₹ Lakh) | B9: =B4 -> 4561.2 | C9: Cross-check
A10: Margin of Safety (₹ Lakh) | B10: =B9-B8 -> 1039.4422
A11: Margin of Safety % | B11: =B10/B9 -> 0.22788788
A12: Occupancy at Break-Even (approx., %) | B12: ='12_Revenue'!F5*B8/B9 -> 0.52503624 | C12: Break-even revenue ÷ actual revenue × actual occupancy (linear approximation)
A14: This is a simplified contribution-margin break-even for management discussion, not a full activity-based costing exercise. The staff-cost line is treated as fixed because in a hospital, clinical staffing is sized to licensed capacity and shift rosters, not to daily patient volume.

Sheet 16_Sensitivity
A1: SENSITIVITY & SCENARIO ANALYSIS
A2: Impact of key drivers on Year 5 EBITDA and 10-yr project economics
A3: A. YEAR-5 EBITDA SENSITIVITY TO OCCUPANCY (± vs Base Case Yr5 target)
A4: Occupancy Scenario | B4: Occupancy % | C4: Net Revenue (₹ Lakh, approx.) | D4: EBITDA (₹ Lakh, approx.) | E4: EBITDA Margin % | F4: Note
A5: Downside (–15pp) | B5: ='12_Revenue'!F5+-0.15 -> 0.53 | C5: ='12_Revenue'!F9*(B5/'12_Revenue'!F5)*(1-'02_Assumptions'!$C$27) -> 3555.0802 | D5: =C5-'15_Break_Even'!$B$6-'15_Break_Even'!$B$5*(C5/'15_Break_Even'!$B$4) -> 28.82654 | E5: =D5/C5 -> 0.0081085484
A6: Downside (–10pp) | B6: ='12_Revenue'!F5+-0.1 -> 0.58 | C6: ='12_Revenue'!F9*(B6/'12_Revenue'!F5)*(1-'02_Assumptions'!$C$27) -> 3890.4651 | D6: =C6-'15_Break_Even'!$B$6-'15_Break_Even'!$B$5*(C6/'15_Break_Even'!$B$4) -> 318.96112 | E6: =D6/C6 -> 0.081985343
A7: Base Case | B7: ='12_Revenue'!F5+0 -> 0.68 | C7: ='12_Revenue'!F9*(B7/'12_Revenue'!F5)*(1-'02_Assumptions'!$C$27) -> 4561.235 | D7: =C7-'15_Break_Even'!$B$6-'15_Break_Even'!$B$5*(C7/'15_Break_Even'!$B$4) -> 899.23028 | E7: =D7/C7 -> 0.19714623 | F7: Base Case row anchors to 12_Revenue / 15_Break_Even live values
A8: Upside (+10pp) | B8: ='12_Revenue'!F5+0.1 -> 0.78 | C8: ='12_Revenue'!F9*(B8/'12_Revenue'!F5)*(1-'02_Assumptions'!$C$27) -> 5232.0049 | D8: =C8-'15_Break_Even'!$B$6-'15_Break_Even'!$B$5*(C8/'15_Break_Even'!$B$4) -> 1479.4994 | E8: =D8/C8 -> 0.28277868
A9: Upside (+15pp) | B9: ='12_Revenue'!F5+0.15 -> 0.83 | C9: ='12_Revenue'!F9*(B9/'12_Revenue'!F5)*(1-'02_Assumptions'!$C$27) -> 5567.3898 | D9: =C9-'15_Break_Even'!$B$6-'15_Break_Even'!$B$5*(C9/'15_Break_Even'!$B$4) -> 1769.634 | E9: =D9/C9 -> 0.31785704
A11: B. CAPEX SCENARIO COMPARISON (LEAN / BASE / UPPER)
A12: Metric | B12: Lean Case | C12: Base Case | D12: Upper Case
A13: Total CAPEX (₹ Cr) | B13: ='10_CAPEX'!B11 -> 40 | C13: ='10_CAPEX'!C11 -> 50 | D13: ='10_CAPEX'!D11 -> 60
A14: Approx. Year-5 EBITDA (₹ Lakh) — scaled by relative equipment/capacity intensity | B14: =C13*0.85 -> 42.5 | C14: ='13_PL'!F6 -> 899.2 | D14: =C13*1.12 -> 56
A15: Directional Payback Period (years, EBITDA-based, illustrative) | B15: =B13*100/B14 -> 94.117647 | C15: =C13*100/C14 -> 5.5604982 | D15: =D13*100/D14 -> 107.14286
A17: Lean/Upper Year-5 EBITDA figures are directional scaling (not fully re-modelled P&Ls) reflecting that a leaner CAPEX build implies fewer high-end service lines (e.g. deferred MRI/Cath Lab) while an upper-case build supports faster service-line expansion and a modestly higher revenue ceiling. For a bank-grade appraisal, each case should be independently modelled in 10_CAPEX through 14_Cash_Flow.

Sheet 17_Operations_KPIs
A1: OPERATIONAL KPI DASHBOARD (TARGETS)
A2: Mature-year (Year 5) operating targets
A3: KPI | B3: Target | C3: Industry Benchmark Range | D3: Note
A4: Average Occupancy Rate | B4: ='12_Revenue'!F5 -> 0.68 | C4: 55%–70% | D4: Mature-year target; below 50% signals demand-generation gap
A5: Average Length of Stay (ALOS) | B5: ='02_Assumptions'!$C$16 -> 3.8 | C5: 3.5–4.5 days | D5: Case-mix dependent
A6: Bed Turnover Ratio | B6: =ROUND(365/'02_Assumptions'!$C$16*'12_Revenue'!F5,1) -> 65.3 | C6: 45–60 times/bed/yr
A7: OPD to IPD Conversion Ratio | B7: ='02_Assumptions'!$C$21 -> 0.08 | C7: 6%–10%
A8: OT Utilisation Rate | B8: 0.65 | C8: 60%–75% | D8: Assumption — scheduled OT hours used / available OT hours
A9: ICU Occupancy Rate | B9: 0.7 | C9: 65%–80% | D9: Assumption
A10: Emergency Department Turnaround Time (median) | B10: < 2 hours | C10: 1.5–3 hours | D10: Door-to-decision benchmark
A11: Patient Satisfaction Score (target) | B11: 0.85 | C11: 80%–90% | D11: Assumption — CSAT survey target
A12: Staff Attrition Rate (clinical, annual) | B12: 0.12 | C12: 10%–18% (hill-state) | D12: Retention risk flagged in 08_Department_Planning/Manpower notes
A13: Revenue per Occupied Bed Day (Year 5, ₹) | B13: ='12_Revenue'!F7 -> 11993.531 | C13: ₹8,000–₹14,000 (Tier-2/3)
A14: EBITDA Margin (Year 5) | B14: ='11_OPEX'!F12 -> 0.1971411 | C14: 15%–22% (mature) | D14: Model shows a longer ramp — see 13_P&L narrative

Sheet 18_Patient_Flow
A1: PATIENT FLOW MAP
A2: OPD-to-discharge journey and Emergency pathway
A3: A. OPD → ADMISSION PATHWAY
A4: 1 | B4: Registration & Triage | C4: Patient registers at front desk / online appointment; vitals & triage nurse assessment
A5: 2 | B5: OPD Consultation | C5: Consultant evaluates; orders diagnostics if required
A6: 3 | B6: Diagnostics | C6: Lab / imaging performed; results routed to consultant via HIS
A7: 4 | B7: Clinical Decision | C7: Consultant reviews results — discharge with prescription, follow-up, or admit
A8: 5 | B8: Admission (if required) | C8: Bed allotment via HIS bed-management module; pre-admission counselling & billing estimate
A9: 6 | B9: IPD Care | C9: Ward/ICU care, nursing rounds, consultant rounds, daily progress notes in EMR
A10: 7 | B10: Discharge Planning | C10: Discharge summary, medication reconciliation, follow-up appointment, billing settlement
A11: 8 | B11: Post-Discharge Follow-up | C11: Tele-follow-up call / OPD review appointment; feedback/CSAT survey
A13: B. EMERGENCY PATHWAY
A14: 1 | B14: Arrival & Triage | C14: Colour-coded triage (Red/Yellow/Green) within 5 minutes of arrival
A15: 2 | B15: Resuscitation / Stabilisation | C15: Immediate stabilisation for Red-category patients
A16: 3 | B16: Clinical Assessment | C16: Duty doctor assessment, diagnostics ordered on priority basis
A17: 4 | B17: Disposition Decision | C17: Discharge, ICU admission, ward admission, or transfer-out (if beyond facility capability)
A18: 5 | B18: Admission / Transfer | C18: Bed allotment or coordinated transfer to a higher-centre with documentation
A20: This flow map is the basis for the swimlane process diagram in the Operations SOP document and for the OPD/Emergency KPIs tracked in the Analytics sheets.

Sheet 19_NABH_Readiness
A1: NABH ACCREDITATION READINESS TRACKER
A2: 10 NABH chapters — self-assessed readiness stage for a greenfield hospital
A3: Code | B3: NABH Chapter | C3: Target Readiness (by launch) | D3: Key Actions
A4: AAC | B4: Access, Assessment & Continuity of Care | C4: In Progress | D4: Standardise triage, assessment formats and referral/transfer protocols
A5: COP | B5: Care of Patients | C5: In Progress | D5: Clinical protocols, informed consent formats, high-risk patient identification
A6: MOM | B6: Management of Medication | C6: Planned | D6: Drug formulary, high-alert medication protocol, pharmacy verification workflow
A7: PRE | B7: Patient Rights & Education | C7: Planned | D7: Patient charter, grievance redressal, health education material
A8: HIC | B8: Hospital Infection Control | C8: In Progress | D8: Infection control committee, hand-hygiene audits, biomedical waste SOP
A9: PSQ | B9: Patient Safety & Quality Improvement | C9: Planned | D9: Incident reporting system, quality indicators dashboard (links to Analytics sheets)
A10: ROM | B10: Responsibilities of Management | C10: In Progress | D10: Governance structure, policy approval workflow, budgeting cycle
A11: FMS | B11: Facility Management & Safety | C11: In Progress | D11: Fire-NOC, disaster management plan, biomedical equipment maintenance schedule
A12: HRM | B12: Human Resource Management | C12: Planned | D12: Credentialing & privileging, induction & CME tracking, performance appraisal
A13: IMS | B13: Information Management System | C13: Planned | D13: HIS/EMR rollout, medical record retention policy, data backup & security
A15: Standard used per NABH's public 10-chapter framework naming convention (AAC through IMS). Readiness staging (In Progress/Planned) is the project team's own planning judgement for a hypothetical greenfield hospital, not an actual NABH assessment or certification status.

Sheet 20_Competitor_Benchmark
A1: COMPETITOR BENCHMARKING
A2: Positioning vs. key players in and beyond the corridor
A3: Dimension | B3: Fortis Kangra (Private) | C3: RPGMC Tanda (Govt. Tertiary) | D3: Max/Fortis Chandigarh-Delhi (Out-of-state Referral) | E3: Hospital 360 (Proposed)
A4: Approx. bed strength | B4: ~100 | C4: ~950 | D4: 300–1000+ | E4: 100 (licensed), 78 at launch
A5: Positioning | B5: Private secondary/tertiary care in-corridor | C5: Public tertiary teaching hospital, high volume, budget-priced | D5: Premium tertiary/quaternary, long travel for local patients | E5: Trusted private multispecialty with NABH-oriented quality, local accessibility
A6: Price point | B6: Mid-to-premium private pricing | C6: Low-cost/subsidised | D6: Premium, plus travel & stay cost for patients | E6: Mid-market — positioned between Govt. and out-of-state premium
A7: Key strength | B7: Established private brand, already in-market | C7: Scale, subsidised cost, academic backing | D7: Advanced tertiary/quaternary capability | E7: Local accessibility + tourism-linked wellness + faster access to advanced diagnostics than Govt.
A8: Key gap it can address | B8: — | C8: Long wait times, capacity strain, limited private-room comfort | D8: Distance, cost, travel burden for local families | E8: Reduces 'travel to Chandigarh/Delhi' need for mid-complexity tertiary care
A9: Strategic response for Hospital 360 | B9: Differentiate on turnaround time, comfort, patient experience | C9: Differentiate on speed of access, private-room comfort, service consistency | D9: Position as the 'first stop' for tertiary care, referring upward only for quaternary/super-specialised cases | E9: —
A11: Bed-strength and presence of Fortis Kangra and RPGMC Tanda are Actual Public Data (see Source_Register); positioning language, pricing tiers and strategic-response commentary are the project team's own competitive analysis, not published statements by these institutions.

Sheet 21_Analytics_OPD
A1: ANALYTICS — OPD FOOTFALL & CASE-MIX
A2: ⚠ SYNTHETIC DATA — generated for this academic model to demonstrate the analytics layer. Not real patient or hospital data.
B3: Apr-2025 | C3: May-2025 | D3: Jun-2025 | E3: Jul-2025 | F3: Aug-2025 | G3: Sep-2025 | H3: Oct-2025 | I3: Nov-2025 | J3: Dec-2025 | K3: Jan-2026 | L3: Feb-2026 | M3: Mar-2026 | N3: Apr-2026 | O3: May-2026 | P3: Jun-2026 | Q3: Jul-2026 | R3: Aug-2026 | S3: Sep-2026 | T3: Oct-2026 | U3: Nov-2026 | V3: Dec-2026 | W3: Jan-2027 | X3: Feb-2027 | Y3: Mar-2027
A4: Total OPD Footfall | B4: 6208.4 | C4: 5978.1 | D4: 5923.8 | E4: 5831.1 | F4: 6106.3 | G4: 6343.5 | H4: 6740 | I4: 6563.9 | J4: 6625.9 | K4: 6406.6 | L4: 6319.3 | M4: 6436.9 | N4: 6211.9 | O4: 6106.9 | P4: 6324.7 | Q4: 6470.9 | R4: 6386.1 | S4: 6565.3 | T4: 6906.3 | U4: 6675.3 | V4: 7015.6 | W4: 7284.6 | X4: 7300.7 | Y4: 7184
A5: New Patients | B5: 2462 | C5: 2074 | D5: 1940 | E5: 1911 | F5: 2368 | G5: 2336 | H5: 2592 | I5: 2484 | J5: 2405 | K5: 2549 | L5: 2214 | M5: 2344 | N5: 2400 | O5: 2256 | P5: 2460 | Q5: 2370 | R5: 2404 | S5: 2125 | T5: 2336 | U5: 2291 | V5: 2290 | W5: 2467 | X5: 2395 | Y5: 2459
A6: Follow-up Patients | B6: 3746 | C6: 3904 | D6: 3984 | E6: 3920 | F6: 3738 | G6: 4008 | H6: 4148 | I6: 4080 | J6: 4221 | K6: 3858 | L6: 4105 | M6: 4093 | N6: 3812 | O6: 3851 | P6: 3865 | Q6: 4101 | R6: 3982 | S6: 4440 | T6: 4570 | U6: 4384 | V6: 4726 | W6: 4818 | X6: 4906 | Y6: 4725
A7: OPD→IPD Conversion Rate | B7: 530.367 | C7: 445.926 | D7: 443.143 | E7: 398.732 | F7: 431.588 | G7: 618.277 | H7: 579.11 | I7: 553.765 | J7: 442.912 | K7: 571.245 | L7: 420.462 | M7: 483.915 | N7: 618.587 | O7: 522.751 | P7: 520.384 | Q7: 565.457 | R7: 598.467 | S7: 597.705 | T7: 477.653 | U7: 409.089 | V7: 509.46 | W7: 515.091 | X7: 499.655 | Y7: 701.995
A8: Department-wise OPD Share (avg. of period, synthetic)
A9: General Medicine | B9: 0.2
A10: Obstetrics & Gynaecology | B10: 0.16
A11: Paediatrics | B11: 0.14
A12: Orthopaedics | B12: 0.13
A13: General Surgery | B13: 0.1
A14: ENT/Ophthalmology | B14: 0.09
A15: Skin/Dermatology | B15: 0.08
A16: Others | B16: 0.1

Sheet 22_Analytics_IPD
A1: ANALYTICS — IPD ADMISSIONS & ALOS
A2: ⚠ SYNTHETIC DATA — generated for this academic model to demonstrate the analytics layer. Not real patient or hospital data.
B3: Apr-2025 | C3: May-2025 | D3: Jun-2025 | E3: Jul-2025 | F3: Aug-2025 | G3: Sep-2025 | H3: Oct-2025 | I3: Nov-2025 | J3: Dec-2025 | K3: Jan-2026 | L3: Feb-2026 | M3: Mar-2026 | N3: Apr-2026 | O3: May-2026 | P3: Jun-2026 | Q3: Jul-2026 | R3: Aug-2026 | S3: Sep-2026 | T3: Oct-2026 | U3: Nov-2026 | V3: Dec-2026 | W3: Jan-2027 | X3: Feb-2027 | Y3: Mar-2027
A4: IPD Admissions | B4: 302.5 | C4: 300.2 | D4: 313.2 | E4: 314.8 | F4: 339.6 | G4: 344.6 | H4: 340.9 | I4: 336.4 | J4: 345.9 | K4: 342.2 | L4: 352.8 | M4: 377.7 | N4: 380.7 | O4: 375.8 | P4: 405.6 | Q4: 414.1 | R4: 404.1 | S4: 391.9 | T4: 382.2 | U4: 395.6 | V4: 416.6 | W4: 421.4 | X4: 410.3 | Y4: 413.2
A5: ALOS (days) | B5: 4.3 | C5: 3.8 | D5: 4.3 | E5: 4.2 | F5: 3.3 | G5: 4 | H5: 4 | I5: 3.8 | J5: 3.6 | K5: 3.9 | L5: 3.4 | M5: 3.7 | N5: 3.8 | O5: 4.3 | P5: 4.2 | Q5: 3.6 | R5: 3.8 | S5: 3.5 | T5: 4.2 | U5: 4.2 | V5: 3.6 | W5: 3.9 | X5: 3.9 | Y5: 3.5
A6: Patient Days | B6: 1301 | C6: 1141 | D6: 1347 | E6: 1322 | F6: 1121 | G6: 1378 | H6: 1364 | I6: 1278 | J6: 1245 | K6: 1335 | L6: 1200 | M6: 1397 | N6: 1447 | O6: 1616 | P6: 1704 | Q6: 1491 | R6: 1536 | S6: 1372 | T6: 1605 | U6: 1662 | V6: 1500 | W6: 1643 | X6: 1600 | Y6: 1446
A7: 30-Day Readmission Rate | B7: 0.039 | C7: 0.033 | D7: 0.039 | E7: 0.033 | F7: 0.02 | G7: 0.028 | H7: 0.02 | I7: 0.043 | J7: 0.042 | K7: 0.041 | L7: 0.028 | M7: 0.021 | N7: 0.042 | O7: 0.044 | P7: 0.022 | Q7: 0.032 | R7: 0.022 | S7: 0.039 | T7: 0.039 | U7: 0.023 | V7: 0.032 | W7: 0.034 | X7: 0.027 | Y7: 0.042

Sheet 23_Analytics_Emergency_OT
A1: ANALYTICS — EMERGENCY & OT UTILISATION
A2: ⚠ SYNTHETIC DATA — generated for this academic model to demonstrate the analytics layer. Not real patient or hospital data.
B3: Apr-2025 | C3: May-2025 | D3: Jun-2025 | E3: Jul-2025 | F3: Aug-2025 | G3: Sep-2025 | H3: Oct-2025 | I3: Nov-2025 | J3: Dec-2025 | K3: Jan-2026 | L3: Feb-2026 | M3: Mar-2026 | N3: Apr-2026 | O3: May-2026 | P3: Jun-2026 | Q3: Jul-2026 | R3: Aug-2026 | S3: Sep-2026 | T3: Oct-2026 | U3: Nov-2026 | V3: Dec-2026 | W3: Jan-2027 | X3: Feb-2027 | Y3: Mar-2027
A4: Emergency Visits | B4: 954 | C4: 930 | D4: 949.2 | E4: 994 | F4: 969.2 | G4: 958.7 | H4: 1038.9 | I4: 1074.4 | J4: 1082.3 | K4: 1100.9 | L4: 1067 | M4: 1046.4 | N4: 1040.5 | O4: 1067.9 | P4: 1048 | Q4: 1026.5 | R4: 984.9 | S4: 1017.1 | T4: 996.3 | U4: 1065.1 | V4: 1128.9 | W4: 1088.8 | X4: 1070.3 | Y4: 1108.8
A5: ER→Admission Rate | B5: 0.197 | C5: 0.191 | D5: 0.255 | E5: 0.226 | F5: 0.218 | G5: 0.243 | H5: 0.245 | I5: 0.195 | J5: 0.188 | K5: 0.214 | L5: 0.214 | M5: 0.217 | N5: 0.238 | O5: 0.234 | P5: 0.259 | Q5: 0.188 | R5: 0.212 | S5: 0.207 | T5: 0.249 | U5: 0.2 | V5: 0.195 | W5: 0.216 | X5: 0.214 | Y5: 0.202
A6: OT Cases Performed | B6: 117.6 | C6: 128.1 | D6: 129.5 | E6: 139.1 | F6: 142.8 | G6: 137 | H6: 149.4 | I6: 158.8 | J6: 171 | K6: 182.6 | L6: 192.9 | M6: 190.4 | N6: 193.9 | O6: 192.3 | P6: 194.3 | Q6: 189.7 | R6: 191.1 | S6: 204.3 | T6: 203.9 | U6: 213.4 | V6: 216.8 | W6: 219.7 | X6: 232.8 | Y6: 247
A7: OT Utilisation Rate | B7: 0.661 | C7: 0.694 | D7: 0.581 | E7: 0.609 | F7: 0.744 | G7: 0.666 | H7: 0.658 | I7: 0.7 | J7: 0.561 | K7: 0.667 | L7: 0.651 | M7: 0.721 | N7: 0.581 | O7: 0.742 | P7: 0.566 | Q7: 0.587 | R7: 0.669 | S7: 0.685 | T7: 0.597 | U7: 0.574 | V7: 0.728 | W7: 0.599 | X7: 0.669 | Y7: 0.674

Sheet 24_Analytics_Diag_Pharmacy
A1: ANALYTICS — DIAGNOSTICS & PHARMACY
A2: ⚠ SYNTHETIC DATA — generated for this academic model to demonstrate the analytics layer. Not real patient or hospital data.
B3: Apr-2025 | C3: May-2025 | D3: Jun-2025 | E3: Jul-2025 | F3: Aug-2025 | G3: Sep-2025 | H3: Oct-2025 | I3: Nov-2025 | J3: Dec-2025 | K3: Jan-2026 | L3: Feb-2026 | M3: Mar-2026 | N3: Apr-2026 | O3: May-2026 | P3: Jun-2026 | Q3: Jul-2026 | R3: Aug-2026 | S3: Sep-2026 | T3: Oct-2026 | U3: Nov-2026 | V3: Dec-2026 | W3: Jan-2027 | X3: Feb-2027 | Y3: Mar-2027
A4: Lab Tests Performed | B4: 9078.2 | C4: 9365.2 | D4: 9581.2 | E4: 10320.6 | F4: 10154.4 | G4: 10629.8 | H4: 10513.2 | I4: 10592.1 | J4: 11020.3 | K4: 10988.7 | L4: 10976.9 | M4: 11513.8 | N4: 11205.4 | O4: 11377 | P4: 12232.6 | Q4: 13102.3 | R4: 12826.7 | S4: 12721.8 | T4: 12680.4 | U4: 13479.9 | V4: 14229.4 | W4: 14991.8 | X4: 15127.3 | Y4: 14998.6
A5: Imaging Studies Performed | B5: 1502.8 | C5: 1578.4 | D5: 1635 | E5: 1776.8 | F5: 1846.9 | G5: 1773.5 | H5: 1880.1 | I5: 1872.7 | J5: 1946.8 | K5: 2084 | L5: 2043.8 | M5: 1998.5 | N5: 1950.5 | O5: 2001.4 | P5: 1990.4 | Q5: 2053.7 | R5: 2143.5 | S5: 2120 | T5: 2192.5 | U5: 2183.5 | V5: 2224.6 | W5: 2359.9 | X5: 2484.6 | Y5: 2442.9
A6: Pharmacy Prescriptions Filled | B6: 7554.8 | C6: 7456.3 | D6: 7069.2 | E6: 7481.1 | F6: 7759.7 | G6: 7649.5 | H6: 8040.5 | I6: 8239.4 | J6: 8311.8 | K6: 7946.6 | L6: 7643.6 | M6: 8183.5 | N6: 8754.9 | O6: 8960.4 | P6: 9473 | Q6: 9730.1 | R6: 9535.8 | S6: 9316.2 | T6: 9282.6 | U6: 9868.6 | V6: 10357.2 | W6: 10922.3 | X6: 11537.8 | Y6: 11441.1
A7: Avg Lab TAT (hours) | B7: 1.9 | C7: 1.7 | D7: 2.7 | E7: 2.8 | F7: 2.1 | G7: 2.4 | H7: 1.7 | I7: 2.9 | J7: 2.8 | K7: 3 | L7: 2.7 | M7: 2.8 | N7: 1.5 | O7: 2.6 | P7: 2 | Q7: 2.9 | R7: 2.7 | S7: 2.8 | T7: 2.7 | U7: 1.9 | V7: 2.7 | W7: 1.7 | X7: 2.8 | Y7: 2.8

Sheet 25_Analytics_Beds_Occupancy
A1: ANALYTICS — BED OCCUPANCY BY WARD
A2: ⚠ SYNTHETIC DATA — generated for this academic model to demonstrate the analytics layer. Not real patient or hospital data.
B3: Apr-2025 | C3: May-2025 | D3: Jun-2025 | E3: Jul-2025 | F3: Aug-2025 | G3: Sep-2025 | H3: Oct-2025 | I3: Nov-2025 | J3: Dec-2025 | K3: Jan-2026 | L3: Feb-2026 | M3: Mar-2026 | N3: Apr-2026 | O3: May-2026 | P3: Jun-2026 | Q3: Jul-2026 | R3: Aug-2026 | S3: Sep-2026 | T3: Oct-2026 | U3: Nov-2026 | V3: Dec-2026 | W3: Jan-2027 | X3: Feb-2027 | Y3: Mar-2027
A4: General Ward Occupancy | B4: 0.333 | C4: 0.382 | D4: 0.374 | E4: 0.377 | F4: 0.42 | G4: 0.399 | H4: 0.399 | I4: 0.423 | J4: 0.444 | K4: 0.489 | L4: 0.508 | M4: 0.48 | N4: 0.514 | O4: 0.513 | P4: 0.561 | Q4: 0.547 | R4: 0.584 | S4: 0.548 | T4: 0.612 | U4: 0.578 | V4: 0.638 | W4: 0.609 | X4: 0.613 | Y4: 0.645
A5: ICU/HDU Occupancy | B5: 0.418 | C5: 0.399 | D5: 0.436 | E5: 0.443 | F5: 0.447 | G5: 0.476 | H5: 0.464 | I5: 0.515 | J5: 0.472 | K5: 0.56 | L5: 0.543 | M5: 0.572 | N5: 0.587 | O5: 0.596 | P5: 0.585 | Q5: 0.576 | R5: 0.637 | S5: 0.624 | T5: 0.637 | U5: 0.694 | V5: 0.698 | W5: 0.678 | X5: 0.693 | Y5: 0.715
A6: Maternity Occupancy | B6: 0.374 | C6: 0.378 | D6: 0.378 | E6: 0.405 | F6: 0.446 | G6: 0.441 | H6: 0.464 | I6: 0.457 | J6: 0.448 | K6: 0.473 | L6: 0.45 | M6: 0.477 | N6: 0.496 | O6: 0.515 | P6: 0.529 | Q6: 0.528 | R6: 0.537 | S6: 0.533 | T6: 0.558 | U6: 0.594 | V6: 0.598 | W6: 0.57 | X6: 0.575 | Y6: 0.611
A7: Blended Occupancy | B7: 0.375 | C7: 0.386 | D7: 0.396 | E7: 0.408 | F7: 0.438 | G7: 0.439 | H7: 0.442 | I7: 0.465 | J7: 0.455 | K7: 0.507 | L7: 0.5 | M7: 0.51 | N7: 0.532 | O7: 0.541 | P7: 0.558 | Q7: 0.55 | R7: 0.586 | S7: 0.568 | T7: 0.602 | U7: 0.622 | V7: 0.645 | W7: 0.619 | X7: 0.627 | Y7: 0.657

Sheet 26_Analytics_Revenue
A1: ANALYTICS — MONTHLY REVENUE BY STREAM
A2: ⚠ SYNTHETIC DATA — generated for this academic model to demonstrate the analytics layer. Not real patient or hospital data.
B3: Apr-2025 | C3: May-2025 | D3: Jun-2025 | E3: Jul-2025 | F3: Aug-2025 | G3: Sep-2025 | H3: Oct-2025 | I3: Nov-2025 | J3: Dec-2025 | K3: Jan-2026 | L3: Feb-2026 | M3: Mar-2026 | N3: Apr-2026 | O3: May-2026 | P3: Jun-2026 | Q3: Jul-2026 | R3: Aug-2026 | S3: Sep-2026 | T3: Oct-2026 | U3: Nov-2026 | V3: Dec-2026 | W3: Jan-2027 | X3: Feb-2027 | Y3: Mar-2027
A4: IPD Revenue (₹ Lakh) | B4: 98.9 | C4: 98.8 | D4: 105.3 | E4: 110.9 | F4: 115.6 | G4: 114.5 | H4: 113 | I4: 109.2 | J4: 108.2 | K4: 110.3 | L4: 117.3 | M4: 114.2 | N4: 115.6 | O4: 119.9 | P4: 118.5 | Q4: 123.7 | R4: 126.3 | S4: 125.7 | T4: 130.5 | U4: 126.8 | V4: 133 | W4: 139.5 | X4: 137.3 | Y4: 139.3
A5: OPD Revenue (₹ Lakh) | B5: 21.3 | C5: 23.2 | D5: 23.7 | E5: 22.6 | F5: 22.1 | G5: 23.7 | H5: 24 | I5: 25.5 | J5: 26.5 | K5: 28.7 | L5: 29.6 | M5: 31.7 | N5: 33.7 | O5: 34.7 | P5: 36 | Q5: 36.7 | R5: 38.5 | S5: 39.4 | T5: 41.5 | U5: 43.1 | V5: 43.8 | W5: 43.7 | X5: 43.6 | Y5: 44.9
A6: Diagnostics Revenue (₹ Lakh) | B6: 19.1 | C6: 19.5 | D6: 20.2 | E6: 19.9 | F6: 19.1 | G6: 18.8 | H6: 18.5 | I6: 18.3 | J6: 18.7 | K6: 18 | L6: 17.6 | M6: 18.5 | N6: 19.4 | O6: 18.5 | P6: 18.5 | Q6: 19 | R6: 19.1 | S6: 18.6 | T6: 18.7 | U6: 20.2 | V6: 20.8 | W6: 21.7 | X6: 23.2 | Y6: 24.3
A7: Pharmacy Revenue (₹ Lakh) | B7: 13 | C7: 12.3 | D7: 12.2 | E7: 12.9 | F7: 13.7 | G7: 14.8 | H7: 14.9 | I7: 15.6 | J7: 15.9 | K7: 16.3 | L7: 16.1 | M7: 15.8 | N7: 16 | O7: 15.4 | P7: 15.3 | Q7: 15.9 | R7: 16 | S7: 15.6 | T7: 15.8 | U7: 15.4 | V7: 15.8 | W7: 15.2 | X7: 15.3 | Y7: 15.6
A8: Total Monthly Revenue (₹ Lakh) | B8: =SUM(B4:B7) -> 152.3 | C8: =SUM(C4:C7) -> 153.8 | D8: =SUM(D4:D7) -> 161.4 | E8: =SUM(E4:E7) -> 166.3 | F8: =SUM(F4:F7) -> 170.5 | G8: =SUM(G4:G7) -> 171.8 | H8: =SUM(H4:H7) -> 170.4 | I8: =SUM(I4:I7) -> 168.6 | ... Y8: =SUM(Y4:Y7) -> 224.1

Sheet 27_Analytics_Quality
A1: ANALYTICS — QUALITY & SAFETY INDICATORS
A2: ⚠ SYNTHETIC DATA — generated for this academic model to demonstrate the analytics layer. Not real patient or hospital data.
B3: Apr-2025 | C3: May-2025 | D3: Jun-2025 | E3: Jul-2025 | F3: Aug-2025 | G3: Sep-2025 | H3: Oct-2025 | I3: Nov-2025 | J3: Dec-2025 | K3: Jan-2026 | L3: Feb-2026 | M3: Mar-2026 | N3: Apr-2026 | O3: May-2026 | P3: Jun-2026 | Q3: Jul-2026 | R3: Aug-2026 | S3: Sep-2026 | T3: Oct-2026 | U3: Nov-2026 | V3: Dec-2026 | W3: Jan-2027 | X3: Feb-2027 | Y3: Mar-2027
A4: Hospital-Acquired Infection Rate (per 1,000 patient-days) | B4: 0.44 | C4: 1.3 | D4: 0.59 | E4: 1.05 | F4: 0.47 | G4: 0.93 | H4: 0.7 | I4: 0.86 | J4: 1.47 | K4: 0.93 | L4: 1.45 | M4: 1.56 | N4: 0.75 | O4: 0.51 | P4: 0.43 | Q4: 1.16 | R4: 1.8 | S4: 0.89 | T4: 1.31 | U4: 1.49 | V4: 1.31 | W4: 1.46 | X4: 1.73 | Y4: 0.68
A5: Patient Fall Rate (per 1,000 patient-days) | B5: 0.11 | C5: 0.18 | D5: 0.16 | E5: 0.43 | F5: 0.38 | G5: 0.21 | H5: 0.45 | I5: 0.48 | J5: 0.18 | K5: 0.4 | L5: 0.47 | M5: 0.16 | N5: 0.51 | O5: 0.58 | P5: 0.15 | Q5: 0.11 | R5: 0.26 | S5: 0.44 | T5: 0.58 | U5: 0.3 | V5: 0.46 | W5: 0.14 | X5: 0.45 | Y5: 0.41
A6: Medication Error Rate (per 1,000 doses) | B6: 0.08 | C6: 0.28 | D6: 0.31 | E6: 0.23 | F6: 0.09 | G6: 0.35 | H6: 0.28 | I6: 0.15 | J6: 0.18 | K6: 0.16 | L6: 0.2 | M6: 0.15 | N6: 0.3 | O6: 0.3 | P6: 0.08 | Q6: 0.34 | R6: 0.24 | S6: 0.3 | T6: 0.26 | U6: 0.18 | V6: 0.27 | W6: 0.34 | X6: 0.13 | Y6: 0.29
A7: Patient Satisfaction Score (CSAT, %) | B7: 78.2 | C7: 78.3 | D7: 78.4 | E7: 80 | F7: 78.5 | G7: 81.2 | H7: 81.4 | I7: 78.8 | J7: 82.3 | K7: 80.1 | L7: 81.4 | M7: 82.3 | N7: 81.7 | O7: 80.7 | P7: 84.3 | Q7: 82 | R7: 82.4 | S7: 85.1 | T7: 83.7 | U7: 86.2 | V7: 85.8 | W7: 84.5 | X7: 83.7 | Y7: 87.8

Sheet 28_Analytics_HR
A1: ANALYTICS — HR & WORKFORCE INDICATORS
A2: ⚠ SYNTHETIC DATA — generated for this academic model to demonstrate the analytics layer. Not real patient or hospital data.
B3: Apr-2025 | C3: May-2025 | D3: Jun-2025 | E3: Jul-2025 | F3: Aug-2025 | G3: Sep-2025 | H3: Oct-2025 | I3: Nov-2025 | J3: Dec-2025 | K3: Jan-2026 | L3: Feb-2026 | M3: Mar-2026 | N3: Apr-2026 | O3: May-2026 | P3: Jun-2026 | Q3: Jul-2026 | R3: Aug-2026 | S3: Sep-2026 | T3: Oct-2026 | U3: Nov-2026 | V3: Dec-2026 | W3: Jan-2027 | X3: Feb-2027 | Y3: Mar-2027
A4: Total Headcount | B4: 128 | C4: 135 | D4: 137 | E4: 142 | F4: 146 | G4: 149 | H4: 152 | I4: 157 | J4: 156 | K4: 161 | L4: 167 | M4: 168 | N4: 174 | O4: 177 | P4: 181 | Q4: 184 | R4: 189 | S4: 190 | T4: 196 | U4: 197 | V4: 201 | W4: 203 | X4: 207 | Y4: 211
A5: Monthly Attrition Rate | B5: 0.114 | C5: 0.136 | D5: 0.079 | E5: 0.082 | F5: 0.108 | G5: 0.132 | H5: 0.158 | I5: 0.112 | J5: 0.088 | K5: 0.07 | L5: 0.079 | M5: 0.083 | N5: 0.078 | O5: 0.061 | P5: 0.113 | Q5: 0.087 | R5: 0.157 | S5: 0.115 | T5: 0.13 | U5: 0.073 | V5: 0.147 | W5: 0.109 | X5: 0.147 | Y5: 0.117
A6: Vacancy Rate | B6: 0.087 | C6: 0.084 | D6: 0.058 | E6: 0.045 | F6: 0.134 | G6: 0.088 | H6: 0.122 | I6: 0.08 | J6: 0.047 | K6: 0.103 | L6: 0.045 | M6: 0.055 | N6: 0.096 | O6: 0.07 | P6: 0.139 | Q6: 0.052 | R6: 0.116 | S6: 0.101 | T6: 0.119 | U6: 0.063 | V6: 0.092 | W6: 0.085 | X6: 0.084 | Y6: 0.126
A7: Avg Training Hours/Employee | B7: 8.9 | C7: 4.8 | D7: 6.7 | E7: 6.7 | F7: 7.4 | G7: 8.7 | H7: 4.2 | I7: 4.3 | J7: 7 | K7: 3.9 | L7: 4 | M7: 3.5 | N7: 3 | O7: 5.7 | P7: 6.6 | Q7: 4.7 | R7: 4.4 | S7: 7.2 | T7: 7.2 | U7: 5.7 | V7: 7.1 | W7: 8.5 | X7: 7.7 | Y7: 6.8

Sheet 29_Data_Dictionary
A1: DATA DICTIONARY & STAR-SCHEMA NOTES
A2: For the Power BI / analytics layer built on sheets 21–28
A3: FACT TABLES
A4: Table | B4: Grain | C4: Key Measures | D4: Source Sheet
A5: Fact_OPD | B5: Month | C5: Footfall, New/Follow-up split, Conversion Rate | D5: 21_Analytics_OPD
A6: Fact_IPD | B6: Month | C6: Admissions, ALOS, Patient Days, Readmission Rate | D6: 22_Analytics_IPD
A7: Fact_Emergency_OT | B7: Month | C7: ER Visits, Admission Rate, OT Cases, OT Utilisation | D7: 23_Analytics_Emergency_OT
A8: Fact_Diagnostics_Pharmacy | B8: Month | C8: Lab Tests, Imaging Studies, Rx Filled, Lab TAT | D8: 24_Analytics_Diag_Pharmacy
A9: Fact_Bed_Occupancy | B9: Month × Ward | C9: Occupancy % by ward, Blended Occupancy | D9: 25_Analytics_Beds_Occupancy
A10: Fact_Revenue_Monthly | B10: Month × Revenue Stream | C10: IPD/OPD/Diagnostics/Pharmacy Revenue (₹ Lakh) | D10: 26_Analytics_Revenue
A11: Fact_Quality | B11: Month | C11: HAI Rate, Fall Rate, Medication Error Rate, CSAT | D11: 27_Analytics_Quality
A12: Fact_HR | B12: Month | C12: Headcount, Attrition Rate, Vacancy Rate, Training Hours | D12: 28_Analytics_HR
A14: DIMENSION TABLES
A15: Table | B15: Attributes
A16: Dim_Date | B16: Month, Year, Fiscal Year, Phase (Launch/Stabilisation/Mature)
A17: Dim_Department | B17: Department Name, Clinical/Support flag, Phase Introduced
A18: Dim_Ward | B18: Ward Name, Bed Category, Licensed Beds
A19: Dim_Revenue_Stream | B19: Stream Name (IPD/OPD/Diagnostics/Pharmacy)
A21: This star schema (Fact tables 21–28 + Dim_Date/Department/Ward/Revenue_Stream) is the recommended model to load into Power BI Desktop: import each Analytics sheet as a Fact table, build the four Dim tables from their respective columns, then relate on Month/Department/Ward/Stream. See the accompanying Hospital_360_Dashboard.html for a working example of the resulting KPI dashboard, since Power BI Desktop itself is not available in this environment to produce a .pbix file directly.
